{
	"editor": {
		"allAngles": false,
		"entityTextureMode": false
	},
	"textureWidth": 16,
	"textureHeight": 16,
	"textureSizes": {
	},
	"textures": {
		"brass": "/Users/HARPWNER/AppData/Roaming/Vintagestory/assets/survival/textures/block/metal/plate/brass",
		"lead": "/Users/HARPWNER/AppData/Roaming/Vintagestory/assets/survival/textures/block/metal/plate/lead"
	},
	"elements": [
		{
			"name": "Wheel",
			"from": [ 7.0, 6.0, 1.0 ], 
			"to": [ 9.0, 10.0, 7.0 ], 
			"rotationOrigin": [ 7.0, 6.0, 1.0 ],
			"faces": {
				"north": { "texture": "#brass", "uv": [ 5.5, 6.5, 7.5, 10.5 ], "windMode": [-1,-1,-1,-1] },
				"east": { "texture": "#brass", "uv": [ 7.5, 7.0, 13.5, 11.0 ], "windMode": [-1,-1,-1,-1] },
				"south": { "texture": "#brass", "uv": [ 6.0, 8.0, 8.0, 12.0 ], "windMode": [-1,-1,-1,-1] },
				"west": { "texture": "#brass", "uv": [ 8.5, 4.5, 14.5, 8.5 ], "windMode": [-1,-1,-1,-1] },
				"up": { "texture": "#brass", "uv": [ 8.0, 7.5, 10.0, 13.5 ], "windMode": [-1,-1,-1,-1] },
				"down": { "texture": "#brass", "uv": [ 5.0, 8.0, 7.0, 14.0 ], "windMode": [-1,-1,-1,-1] }
			},
			"children": [
				{
					"name": "Cube7",
					"from": [ 2.0, 1.0, -1.0 ], 
					"to": [ 3.0, 3.0, 6.0 ], 
					"rotationOrigin": [ 2.0, 1.0, -1.0 ],
					"faces": {
						"north": { "texture": "#brass", "uv": [ 0.0, 0.0, 1.0, 2.0 ], "reflectiveMode": 2},
						"east": { "texture": "#brass", "uv": [ 0.0, 0.0, 7.0, 2.0 ], "reflectiveMode": 2},
						"south": { "texture": "#brass", "uv": [ 0.0, 0.0, 1.0, 2.0 ], "reflectiveMode": 2},
						"west": { "texture": "#brass", "uv": [ 0.0, 0.0, 7.0, 2.0 ], "reflectiveMode": 2},
						"up": { "texture": "#brass", "uv": [ 0.0, 0.0, 1.0, 7.0 ], "reflectiveMode": 2},
						"down": { "texture": "#brass", "uv": [ 0.0, 0.0, 1.0, 7.0 ], "reflectiveMode": 2}
					}
				},
				{
					"name": "Cube8",
					"from": [ -1.0, 1.0, -1.0 ], 
					"to": [ 0.0, 3.0, 6.0 ], 
					"rotationOrigin": [ -1.0, 1.0, -1.0 ],
					"faces": {
						"north": { "texture": "#brass", "uv": [ 0.0, 0.0, 1.0, 2.0 ], "reflectiveMode": 2},
						"east": { "texture": "#brass", "uv": [ 0.0, 0.0, 7.0, 2.0 ], "reflectiveMode": 2},
						"south": { "texture": "#brass", "uv": [ 0.0, 0.0, 1.0, 2.0 ], "reflectiveMode": 2},
						"west": { "texture": "#brass", "uv": [ 0.0, 0.0, 7.0, 2.0 ], "reflectiveMode": 2},
						"up": { "texture": "#brass", "uv": [ 0.0, 0.0, 1.0, 7.0 ], "reflectiveMode": 2},
						"down": { "texture": "#brass", "uv": [ 0.0, 0.0, 1.0, 7.0 ], "reflectiveMode": 2}
					}
				},
				{
					"name": "Core",
					"from": [ 0.0, 0.0, -1.0 ], 
					"to": [ 2.0, 4.0, 0.0 ], 
					"rotationOrigin": [ 1.0, 2.0, 0.0 ],
					"faces": {
						"north": { "texture": "#brass", "uv": [ 0.0, 0.0, 2.0, 4.0 ], "reflectiveMode": 2},
						"east": { "texture": "#brass", "uv": [ 0.0, 0.0, 1.0, 4.0 ], "reflectiveMode": 2},
						"south": { "texture": "#brass", "uv": [ 0.0, 0.0, 2.0, 4.0 ], "reflectiveMode": 2},
						"west": { "texture": "#brass", "uv": [ 0.0, 0.0, 1.0, 4.0 ], "reflectiveMode": 2},
						"up": { "texture": "#brass", "uv": [ 0.0, 0.0, 2.0, 1.0 ], "reflectiveMode": 2},
						"down": { "texture": "#brass", "uv": [ 0.0, 0.0, 2.0, 1.0 ], "reflectiveMode": 2}
					},
					"children": [
						{
							"name": "spoke40",
							"from": [ 2.0, 1.1, 2.5 ], 
							"to": [ 18.0, 2.9, 4.5 ], 
							"rotationOrigin": [ 1.0, 2.0, 2.0 ],
							"rotationZ": -45.0,
							"faces": {
								"north": { "texture": "#brass", "uv": [ 0.0, 0.0, 16.0, 1.5 ], "reflectiveMode": 2},
								"east": { "texture": "#brass", "uv": [ 0.0, 0.0, 2.0, 1.5 ], "reflectiveMode": 2},
								"south": { "texture": "#brass", "uv": [ 0.0, 0.0, 16.0, 1.5 ], "reflectiveMode": 2},
								"west": { "texture": "#brass", "uv": [ 0.0, 0.0, 2.0, 1.5 ], "reflectiveMode": 2},
								"up": { "texture": "#brass", "uv": [ 0.0, 0.0, 16.0, 2.0 ], "reflectiveMode": 2},
								"down": { "texture": "#brass", "uv": [ 0.0, 0.0, 16.0, 2.0 ], "reflectiveMode": 2}
							}
						},
						{
							"name": "spoke39",
							"from": [ 2.0, 1.1, 2.5 ], 
							"to": [ 18.0, 2.9, 4.5 ], 
							"rotationOrigin": [ 1.0, 2.0, 2.0 ],
							"rotationZ": -90.0,
							"faces": {
								"north": { "texture": "#brass", "uv": [ 0.0, 0.0, 16.0, 1.5 ], "reflectiveMode": 2},
								"east": { "texture": "#brass", "uv": [ 0.0, 0.0, 2.0, 1.5 ], "reflectiveMode": 2},
								"south": { "texture": "#brass", "uv": [ 0.0, 0.0, 16.0, 1.5 ], "reflectiveMode": 2},
								"west": { "texture": "#brass", "uv": [ 0.0, 0.0, 2.0, 1.5 ], "reflectiveMode": 2},
								"up": { "texture": "#brass", "uv": [ 0.0, 0.0, 16.0, 2.0 ], "reflectiveMode": 2},
								"down": { "texture": "#brass", "uv": [ 0.0, 0.0, 16.0, 2.0 ], "reflectiveMode": 2}
							}
						},
						{
							"name": "spoke38",
							"from": [ 2.0, 1.1, 2.5 ], 
							"to": [ 18.0, 2.9, 4.5 ], 
							"rotationOrigin": [ 1.0, 2.0, 2.0 ],
							"rotationZ": -135.0,
							"faces": {
								"north": { "texture": "#brass", "uv": [ 0.0, 0.0, 16.0, 1.5 ], "reflectiveMode": 2},
								"east": { "texture": "#brass", "uv": [ 0.0, 0.0, 2.0, 1.5 ], "reflectiveMode": 2},
								"south": { "texture": "#brass", "uv": [ 0.0, 0.0, 16.0, 1.5 ], "reflectiveMode": 2},
								"west": { "texture": "#brass", "uv": [ 0.0, 0.0, 2.0, 1.5 ], "reflectiveMode": 2},
								"up": { "texture": "#brass", "uv": [ 0.0, 0.0, 16.0, 2.0 ], "reflectiveMode": 2},
								"down": { "texture": "#brass", "uv": [ 0.0, 0.0, 16.0, 2.0 ], "reflectiveMode": 2}
							}
						},
						{
							"name": "spoke37",
							"from": [ 2.0, 1.1, 2.5 ], 
							"to": [ 18.0, 2.9, 4.5 ], 
							"rotationOrigin": [ 1.0, 2.0, 2.0 ],
							"rotationZ": -180.0,
							"faces": {
								"north": { "texture": "#brass", "uv": [ 0.0, 0.0, 16.0, 1.5 ], "reflectiveMode": 2},
								"east": { "texture": "#brass", "uv": [ 0.0, 0.0, 2.0, 1.5 ], "reflectiveMode": 2},
								"south": { "texture": "#brass", "uv": [ 0.0, 0.0, 16.0, 1.5 ], "reflectiveMode": 2},
								"west": { "texture": "#brass", "uv": [ 0.0, 0.0, 2.0, 1.5 ], "reflectiveMode": 2},
								"up": { "texture": "#brass", "uv": [ 0.0, 0.0, 16.0, 2.0 ], "reflectiveMode": 2},
								"down": { "texture": "#brass", "uv": [ 0.0, 0.0, 16.0, 2.0 ], "reflectiveMode": 2}
							}
						},
						{
							"name": "spoke36",
							"from": [ 2.0, 1.1, 2.5 ], 
							"to": [ 18.0, 2.9, 4.5 ], 
							"rotationOrigin": [ 1.0, 2.0, 2.0 ],
							"rotationZ": 135.0,
							"faces": {
								"north": { "texture": "#brass", "uv": [ 0.0, 0.0, 16.0, 1.5 ], "reflectiveMode": 2},
								"east": { "texture": "#brass", "uv": [ 0.0, 0.0, 2.0, 1.5 ], "reflectiveMode": 2},
								"south": { "texture": "#brass", "uv": [ 0.0, 0.0, 16.0, 1.5 ], "reflectiveMode": 2},
								"west": { "texture": "#brass", "uv": [ 0.0, 0.0, 2.0, 1.5 ], "reflectiveMode": 2},
								"up": { "texture": "#brass", "uv": [ 0.0, 0.0, 16.0, 2.0 ], "reflectiveMode": 2},
								"down": { "texture": "#brass", "uv": [ 0.0, 0.0, 16.0, 2.0 ], "reflectiveMode": 2}
							}
						},
						{
							"name": "spoke35",
							"from": [ 2.0, 1.1, 2.5 ], 
							"to": [ 18.0, 2.9, 4.5 ], 
							"rotationOrigin": [ 1.0, 2.0, 2.0 ],
							"rotationZ": 90.0,
							"faces": {
								"north": { "texture": "#brass", "uv": [ 0.0, 0.0, 16.0, 1.5 ], "reflectiveMode": 2},
								"east": { "texture": "#brass", "uv": [ 0.0, 0.0, 2.0, 1.5 ], "reflectiveMode": 2},
								"south": { "texture": "#brass", "uv": [ 0.0, 0.0, 16.0, 1.5 ], "reflectiveMode": 2},
								"west": { "texture": "#brass", "uv": [ 0.0, 0.0, 2.0, 1.5 ], "reflectiveMode": 2},
								"up": { "texture": "#brass", "uv": [ 0.0, 0.0, 16.0, 2.0 ], "reflectiveMode": 2},
								"down": { "texture": "#brass", "uv": [ 0.0, 0.0, 16.0, 2.0 ], "reflectiveMode": 2}
							}
						},
						{
							"name": "spoke",
							"from": [ 2.0, 1.1, 2.5 ], 
							"to": [ 18.0, 2.9, 4.5 ], 
							"rotationOrigin": [ 1.0, 2.0, 2.0 ],
							"faces": {
								"north": { "texture": "#brass", "uv": [ 0.0, 0.0, 16.0, 1.5 ], "reflectiveMode": 2},
								"east": { "texture": "#brass", "uv": [ 0.0, 0.0, 2.0, 1.5 ], "reflectiveMode": 2},
								"south": { "texture": "#brass", "uv": [ 0.0, 0.0, 16.0, 1.5 ], "reflectiveMode": 2},
								"west": { "texture": "#brass", "uv": [ 0.0, 0.0, 2.0, 1.5 ], "reflectiveMode": 2},
								"up": { "texture": "#brass", "uv": [ 0.0, 0.0, 16.0, 2.0 ], "reflectiveMode": 2},
								"down": { "texture": "#brass", "uv": [ 0.0, 0.0, 16.0, 2.0 ], "reflectiveMode": 2}
							}
						},
						{
							"name": "spoke34",
							"from": [ 2.0, 1.1, 2.5 ], 
							"to": [ 18.0, 2.9, 4.5 ], 
							"rotationOrigin": [ 1.0, 2.0, 2.0 ],
							"rotationZ": 45.0,
							"faces": {
								"north": { "texture": "#brass", "uv": [ 0.0, 0.0, 16.0, 1.5 ], "reflectiveMode": 2},
								"east": { "texture": "#brass", "uv": [ 0.0, 0.0, 2.0, 1.5 ], "reflectiveMode": 2},
								"south": { "texture": "#brass", "uv": [ 0.0, 0.0, 16.0, 1.5 ], "reflectiveMode": 2},
								"west": { "texture": "#brass", "uv": [ 0.0, 0.0, 2.0, 1.5 ], "reflectiveMode": 2},
								"up": { "texture": "#brass", "uv": [ 0.0, 0.0, 16.0, 2.0 ], "reflectiveMode": 2},
								"down": { "texture": "#brass", "uv": [ 0.0, 0.0, 16.0, 2.0 ], "reflectiveMode": 2}
							}
						},
						{
							"name": "Outer32",
							"from": [ 18.0, -0.64, 2.0 ], 
							"to": [ 21.0, 4.64, 5.0 ], 
							"rotationOrigin": [ 1.0, 2.0, 2.0 ],
							"rotationZ": -15.0,
							"faces": {
								"north": { "texture": "#brass", "uv": [ 0.0, 0.0, 3.0, 5.0 ], "reflectiveMode": 2},
								"east": { "texture": "#brass", "uv": [ 0.0, 0.0, 3.0, 5.0 ], "reflectiveMode": 2},
								"south": { "texture": "#brass", "uv": [ 0.0, 0.0, 3.0, 5.0 ], "reflectiveMode": 2},
								"west": { "texture": "#brass", "uv": [ 0.0, 0.0, 3.0, 5.0 ], "reflectiveMode": 2},
								"up": { "texture": "#brass", "uv": [ 0.0, 0.0, 3.0, 3.0 ], "reflectiveMode": 2},
								"down": { "texture": "#brass", "uv": [ 0.0, 0.0, 3.0, 3.0 ], "reflectiveMode": 2}
							}
						},
						{
							"name": "Outer31",
							"from": [ 18.0, -0.64, 2.0 ], 
							"to": [ 21.0, 4.64, 5.0 ], 
							"rotationOrigin": [ 1.0, 2.0, 2.0 ],
							"rotationZ": -30.0,
							"faces": {
								"north": { "texture": "#brass", "uv": [ 0.0, 0.0, 3.0, 5.0 ], "reflectiveMode": 2},
								"east": { "texture": "#brass", "uv": [ 0.0, 0.0, 3.0, 5.0 ], "reflectiveMode": 2},
								"south": { "texture": "#brass", "uv": [ 0.0, 0.0, 3.0, 5.0 ], "reflectiveMode": 2},
								"west": { "texture": "#brass", "uv": [ 0.0, 0.0, 3.0, 5.0 ], "reflectiveMode": 2},
								"up": { "texture": "#brass", "uv": [ 0.0, 0.0, 3.0, 3.0 ], "reflectiveMode": 2},
								"down": { "texture": "#brass", "uv": [ 0.0, 0.0, 3.0, 3.0 ], "reflectiveMode": 2}
							}
						},
						{
							"name": "Outer29",
							"from": [ 18.0, -0.64, 2.0 ], 
							"to": [ 21.0, 4.64, 5.0 ], 
							"rotationOrigin": [ 1.0, 2.0, 2.0 ],
							"rotationZ": -60.0,
							"faces": {
								"north": { "texture": "#brass", "uv": [ 0.0, 0.0, 3.0, 5.0 ], "reflectiveMode": 2},
								"east": { "texture": "#brass", "uv": [ 0.0, 0.0, 3.0, 5.0 ], "reflectiveMode": 2},
								"south": { "texture": "#brass", "uv": [ 0.0, 0.0, 3.0, 5.0 ], "reflectiveMode": 2},
								"west": { "texture": "#brass", "uv": [ 0.0, 0.0, 3.0, 5.0 ], "reflectiveMode": 2},
								"up": { "texture": "#brass", "uv": [ 0.0, 0.0, 3.0, 3.0 ], "reflectiveMode": 2},
								"down": { "texture": "#brass", "uv": [ 0.0, 0.0, 3.0, 3.0 ], "reflectiveMode": 2}
							}
						},
						{
							"name": "Outer30",
							"from": [ 18.0, -0.64, 2.0 ], 
							"to": [ 21.0, 4.64, 5.0 ], 
							"rotationOrigin": [ 1.0, 2.0, 2.0 ],
							"rotationZ": -45.0,
							"faces": {
								"north": { "texture": "#brass", "uv": [ 0.0, 0.0, 3.0, 5.0 ], "reflectiveMode": 2},
								"east": { "texture": "#brass", "uv": [ 0.0, 0.0, 3.0, 5.0 ], "reflectiveMode": 2},
								"south": { "texture": "#brass", "uv": [ 0.0, 0.0, 3.0, 5.0 ], "reflectiveMode": 2},
								"west": { "texture": "#brass", "uv": [ 0.0, 0.0, 3.0, 5.0 ], "reflectiveMode": 2},
								"up": { "texture": "#brass", "uv": [ 0.0, 0.0, 3.0, 3.0 ], "reflectiveMode": 2},
								"down": { "texture": "#brass", "uv": [ 0.0, 0.0, 3.0, 3.0 ], "reflectiveMode": 2}
							}
						},
						{
							"name": "Outer28",
							"from": [ 18.0, -0.64, 2.0 ], 
							"to": [ 21.0, 4.64, 5.0 ], 
							"rotationOrigin": [ 1.0, 2.0, 2.0 ],
							"rotationZ": -75.0,
							"faces": {
								"north": { "texture": "#brass", "uv": [ 0.0, 0.0, 3.0, 5.0 ], "reflectiveMode": 2},
								"east": { "texture": "#brass", "uv": [ 0.0, 0.0, 3.0, 5.0 ], "reflectiveMode": 2},
								"south": { "texture": "#brass", "uv": [ 0.0, 0.0, 3.0, 5.0 ], "reflectiveMode": 2},
								"west": { "texture": "#brass", "uv": [ 0.0, 0.0, 3.0, 5.0 ], "reflectiveMode": 2},
								"up": { "texture": "#brass", "uv": [ 0.0, 0.0, 3.0, 3.0 ], "reflectiveMode": 2},
								"down": { "texture": "#brass", "uv": [ 0.0, 0.0, 3.0, 3.0 ], "reflectiveMode": 2}
							}
						},
						{
							"name": "Outer27",
							"from": [ 18.0, -0.64, 2.0 ], 
							"to": [ 21.0, 4.64, 5.0 ], 
							"rotationOrigin": [ 1.0, 2.0, 2.0 ],
							"rotationZ": -90.0,
							"faces": {
								"north": { "texture": "#brass", "uv": [ 0.0, 0.0, 3.0, 5.0 ], "reflectiveMode": 2},
								"east": { "texture": "#brass", "uv": [ 0.0, 0.0, 3.0, 5.0 ], "reflectiveMode": 2},
								"south": { "texture": "#brass", "uv": [ 0.0, 0.0, 3.0, 5.0 ], "reflectiveMode": 2},
								"west": { "texture": "#brass", "uv": [ 0.0, 0.0, 3.0, 5.0 ], "reflectiveMode": 2},
								"up": { "texture": "#brass", "uv": [ 0.0, 0.0, 3.0, 3.0 ], "reflectiveMode": 2},
								"down": { "texture": "#brass", "uv": [ 0.0, 0.0, 3.0, 3.0 ], "reflectiveMode": 2}
							}
						},
						{
							"name": "Outer26",
							"from": [ 18.0, -0.64, 2.0 ], 
							"to": [ 21.0, 4.64, 5.0 ], 
							"rotationOrigin": [ 1.0, 2.0, 2.0 ],
							"rotationZ": -105.0,
							"faces": {
								"north": { "texture": "#brass", "uv": [ 0.0, 0.0, 3.0, 5.0 ], "reflectiveMode": 2},
								"east": { "texture": "#brass", "uv": [ 0.0, 0.0, 3.0, 5.0 ], "reflectiveMode": 2},
								"south": { "texture": "#brass", "uv": [ 0.0, 0.0, 3.0, 5.0 ], "reflectiveMode": 2},
								"west": { "texture": "#brass", "uv": [ 0.0, 0.0, 3.0, 5.0 ], "reflectiveMode": 2},
								"up": { "texture": "#brass", "uv": [ 0.0, 0.0, 3.0, 3.0 ], "reflectiveMode": 2},
								"down": { "texture": "#brass", "uv": [ 0.0, 0.0, 3.0, 3.0 ], "reflectiveMode": 2}
							}
						},
						{
							"name": "Outer25",
							"from": [ 18.0, -0.64, 2.0 ], 
							"to": [ 21.0, 4.64, 5.0 ], 
							"rotationOrigin": [ 1.0, 2.0, 2.0 ],
							"rotationZ": -120.0,
							"faces": {
								"north": { "texture": "#brass", "uv": [ 0.0, 0.0, 3.0, 5.0 ], "reflectiveMode": 2},
								"east": { "texture": "#brass", "uv": [ 0.0, 0.0, 3.0, 5.0 ], "reflectiveMode": 2},
								"south": { "texture": "#brass", "uv": [ 0.0, 0.0, 3.0, 5.0 ], "reflectiveMode": 2},
								"west": { "texture": "#brass", "uv": [ 0.0, 0.0, 3.0, 5.0 ], "reflectiveMode": 2},
								"up": { "texture": "#brass", "uv": [ 0.0, 0.0, 3.0, 3.0 ], "reflectiveMode": 2},
								"down": { "texture": "#brass", "uv": [ 0.0, 0.0, 3.0, 3.0 ], "reflectiveMode": 2}
							}
						},
						{
							"name": "Outer24",
							"from": [ 18.0, -0.64, 2.0 ], 
							"to": [ 21.0, 4.64, 5.0 ], 
							"rotationOrigin": [ 1.0, 2.0, 2.0 ],
							"rotationZ": -135.0,
							"faces": {
								"north": { "texture": "#brass", "uv": [ 0.0, 0.0, 3.0, 5.0 ], "reflectiveMode": 2},
								"east": { "texture": "#brass", "uv": [ 0.0, 0.0, 3.0, 5.0 ], "reflectiveMode": 2},
								"south": { "texture": "#brass", "uv": [ 0.0, 0.0, 3.0, 5.0 ], "reflectiveMode": 2},
								"west": { "texture": "#brass", "uv": [ 0.0, 0.0, 3.0, 5.0 ], "reflectiveMode": 2},
								"up": { "texture": "#brass", "uv": [ 0.0, 0.0, 3.0, 3.0 ], "reflectiveMode": 2},
								"down": { "texture": "#brass", "uv": [ 0.0, 0.0, 3.0, 3.0 ], "reflectiveMode": 2}
							}
						},
						{
							"name": "Outer23",
							"from": [ 18.0, -0.64, 2.0 ], 
							"to": [ 21.0, 4.64, 5.0 ], 
							"rotationOrigin": [ 1.0, 2.0, 2.0 ],
							"rotationZ": -150.0,
							"faces": {
								"north": { "texture": "#brass", "uv": [ 0.0, 0.0, 3.0, 5.0 ], "reflectiveMode": 2},
								"east": { "texture": "#brass", "uv": [ 0.0, 0.0, 3.0, 5.0 ], "reflectiveMode": 2},
								"south": { "texture": "#brass", "uv": [ 0.0, 0.0, 3.0, 5.0 ], "reflectiveMode": 2},
								"west": { "texture": "#brass", "uv": [ 0.0, 0.0, 3.0, 5.0 ], "reflectiveMode": 2},
								"up": { "texture": "#brass", "uv": [ 0.0, 0.0, 3.0, 3.0 ], "reflectiveMode": 2},
								"down": { "texture": "#brass", "uv": [ 0.0, 0.0, 3.0, 3.0 ], "reflectiveMode": 2}
							}
						},
						{
							"name": "Outer22",
							"from": [ 18.0, -0.64, 2.0 ], 
							"to": [ 21.0, 4.64, 5.0 ], 
							"rotationOrigin": [ 1.0, 2.0, 2.0 ],
							"rotationZ": -165.0,
							"faces": {
								"north": { "texture": "#brass", "uv": [ 0.0, 0.0, 3.0, 5.0 ], "reflectiveMode": 2},
								"east": { "texture": "#brass", "uv": [ 0.0, 0.0, 3.0, 5.0 ], "reflectiveMode": 2},
								"south": { "texture": "#brass", "uv": [ 0.0, 0.0, 3.0, 5.0 ], "reflectiveMode": 2},
								"west": { "texture": "#brass", "uv": [ 0.0, 0.0, 3.0, 5.0 ], "reflectiveMode": 2},
								"up": { "texture": "#brass", "uv": [ 0.0, 0.0, 3.0, 3.0 ], "reflectiveMode": 2},
								"down": { "texture": "#brass", "uv": [ 0.0, 0.0, 3.0, 3.0 ], "reflectiveMode": 2}
							}
						},
						{
							"name": "Outer21",
							"from": [ 18.0, -0.64, 2.0 ], 
							"to": [ 21.0, 4.64, 5.0 ], 
							"rotationOrigin": [ 1.0, 2.0, 2.0 ],
							"rotationZ": -180.0,
							"faces": {
								"north": { "texture": "#brass", "uv": [ 0.0, 0.0, 3.0, 5.0 ], "reflectiveMode": 2},
								"east": { "texture": "#brass", "uv": [ 0.0, 0.0, 3.0, 5.0 ], "reflectiveMode": 2},
								"south": { "texture": "#brass", "uv": [ 0.0, 0.0, 3.0, 5.0 ], "reflectiveMode": 2},
								"west": { "texture": "#brass", "uv": [ 0.0, 0.0, 3.0, 5.0 ], "reflectiveMode": 2},
								"up": { "texture": "#brass", "uv": [ 0.0, 0.0, 3.0, 3.0 ], "reflectiveMode": 2},
								"down": { "texture": "#brass", "uv": [ 0.0, 0.0, 3.0, 3.0 ], "reflectiveMode": 2}
							}
						},
						{
							"name": "Outer20",
							"from": [ 18.0, -0.64, 2.0 ], 
							"to": [ 21.0, 4.64, 5.0 ], 
							"rotationOrigin": [ 1.0, 2.0, 2.0 ],
							"rotationZ": 165.0,
							"faces": {
								"north": { "texture": "#brass", "uv": [ 0.0, 0.0, 3.0, 5.0 ], "reflectiveMode": 2},
								"east": { "texture": "#brass", "uv": [ 0.0, 0.0, 3.0, 5.0 ], "reflectiveMode": 2},
								"south": { "texture": "#brass", "uv": [ 0.0, 0.0, 3.0, 5.0 ], "reflectiveMode": 2},
								"west": { "texture": "#brass", "uv": [ 0.0, 0.0, 3.0, 5.0 ], "reflectiveMode": 2},
								"up": { "texture": "#brass", "uv": [ 0.0, 0.0, 3.0, 3.0 ], "reflectiveMode": 2},
								"down": { "texture": "#brass", "uv": [ 0.0, 0.0, 3.0, 3.0 ], "reflectiveMode": 2}
							}
						},
						{
							"name": "Outer19",
							"from": [ 18.0, -0.64, 2.0 ], 
							"to": [ 21.0, 4.64, 5.0 ], 
							"rotationOrigin": [ 1.0, 2.0, 2.0 ],
							"rotationZ": 150.0,
							"faces": {
								"north": { "texture": "#brass", "uv": [ 0.0, 0.0, 3.0, 5.0 ], "reflectiveMode": 2},
								"east": { "texture": "#brass", "uv": [ 0.0, 0.0, 3.0, 5.0 ], "reflectiveMode": 2},
								"south": { "texture": "#brass", "uv": [ 0.0, 0.0, 3.0, 5.0 ], "reflectiveMode": 2},
								"west": { "texture": "#brass", "uv": [ 0.0, 0.0, 3.0, 5.0 ], "reflectiveMode": 2},
								"up": { "texture": "#brass", "uv": [ 0.0, 0.0, 3.0, 3.0 ], "reflectiveMode": 2},
								"down": { "texture": "#brass", "uv": [ 0.0, 0.0, 3.0, 3.0 ], "reflectiveMode": 2}
							}
						},
						{
							"name": "Outer18",
							"from": [ 18.0, -0.64, 2.0 ], 
							"to": [ 21.0, 4.64, 5.0 ], 
							"rotationOrigin": [ 1.0, 2.0, 2.0 ],
							"rotationZ": 135.0,
							"faces": {
								"north": { "texture": "#brass", "uv": [ 0.0, 0.0, 3.0, 5.0 ], "reflectiveMode": 2},
								"east": { "texture": "#brass", "uv": [ 0.0, 0.0, 3.0, 5.0 ], "reflectiveMode": 2},
								"south": { "texture": "#brass", "uv": [ 0.0, 0.0, 3.0, 5.0 ], "reflectiveMode": 2},
								"west": { "texture": "#brass", "uv": [ 0.0, 0.0, 3.0, 5.0 ], "reflectiveMode": 2},
								"up": { "texture": "#brass", "uv": [ 0.0, 0.0, 3.0, 3.0 ], "reflectiveMode": 2},
								"down": { "texture": "#brass", "uv": [ 0.0, 0.0, 3.0, 3.0 ], "reflectiveMode": 2}
							}
						},
						{
							"name": "Outer17",
							"from": [ 18.0, -0.64, 2.0 ], 
							"to": [ 21.0, 4.64, 5.0 ], 
							"rotationOrigin": [ 1.0, 2.0, 2.0 ],
							"rotationZ": 120.0,
							"faces": {
								"north": { "texture": "#brass", "uv": [ 0.0, 0.0, 3.0, 5.0 ], "reflectiveMode": 2},
								"east": { "texture": "#brass", "uv": [ 0.0, 0.0, 3.0, 5.0 ], "reflectiveMode": 2},
								"south": { "texture": "#brass", "uv": [ 0.0, 0.0, 3.0, 5.0 ], "reflectiveMode": 2},
								"west": { "texture": "#brass", "uv": [ 0.0, 0.0, 3.0, 5.0 ], "reflectiveMode": 2},
								"up": { "texture": "#brass", "uv": [ 0.0, 0.0, 3.0, 3.0 ], "reflectiveMode": 2},
								"down": { "texture": "#brass", "uv": [ 0.0, 0.0, 3.0, 3.0 ], "reflectiveMode": 2}
							}
						},
						{
							"name": "Outer16",
							"from": [ 18.0, -0.64, 2.0 ], 
							"to": [ 21.0, 4.64, 5.0 ], 
							"rotationOrigin": [ 1.0, 2.0, 2.0 ],
							"rotationZ": 105.0,
							"faces": {
								"north": { "texture": "#brass", "uv": [ 0.0, 0.0, 3.0, 5.0 ], "reflectiveMode": 2},
								"east": { "texture": "#brass", "uv": [ 0.0, 0.0, 3.0, 5.0 ], "reflectiveMode": 2},
								"south": { "texture": "#brass", "uv": [ 0.0, 0.0, 3.0, 5.0 ], "reflectiveMode": 2},
								"west": { "texture": "#brass", "uv": [ 0.0, 0.0, 3.0, 5.0 ], "reflectiveMode": 2},
								"up": { "texture": "#brass", "uv": [ 0.0, 0.0, 3.0, 3.0 ], "reflectiveMode": 2},
								"down": { "texture": "#brass", "uv": [ 0.0, 0.0, 3.0, 3.0 ], "reflectiveMode": 2}
							}
						},
						{
							"name": "Outer15",
							"from": [ 18.0, -0.64, 2.0 ], 
							"to": [ 21.0, 4.64, 5.0 ], 
							"rotationOrigin": [ 1.0, 2.0, 2.0 ],
							"rotationZ": 90.0,
							"faces": {
								"north": { "texture": "#brass", "uv": [ 0.0, 0.0, 3.0, 5.0 ], "reflectiveMode": 2},
								"east": { "texture": "#brass", "uv": [ 0.0, 0.0, 3.0, 5.0 ], "reflectiveMode": 2},
								"south": { "texture": "#brass", "uv": [ 0.0, 0.0, 3.0, 5.0 ], "reflectiveMode": 2},
								"west": { "texture": "#brass", "uv": [ 0.0, 0.0, 3.0, 5.0 ], "reflectiveMode": 2},
								"up": { "texture": "#brass", "uv": [ 0.0, 0.0, 3.0, 3.0 ], "reflectiveMode": 2},
								"down": { "texture": "#brass", "uv": [ 0.0, 0.0, 3.0, 3.0 ], "reflectiveMode": 2}
							}
						},
						{
							"name": "Outer14",
							"from": [ 18.0, -0.64, 2.0 ], 
							"to": [ 21.0, 4.64, 5.0 ], 
							"rotationOrigin": [ 1.0, 2.0, 2.0 ],
							"rotationZ": 75.0,
							"faces": {
								"north": { "texture": "#brass", "uv": [ 0.0, 0.0, 3.0, 5.0 ], "reflectiveMode": 2},
								"east": { "texture": "#brass", "uv": [ 0.0, 0.0, 3.0, 5.0 ], "reflectiveMode": 2},
								"south": { "texture": "#brass", "uv": [ 0.0, 0.0, 3.0, 5.0 ], "reflectiveMode": 2},
								"west": { "texture": "#brass", "uv": [ 0.0, 0.0, 3.0, 5.0 ], "reflectiveMode": 2},
								"up": { "texture": "#brass", "uv": [ 0.0, 0.0, 3.0, 3.0 ], "reflectiveMode": 2},
								"down": { "texture": "#brass", "uv": [ 0.0, 0.0, 3.0, 3.0 ], "reflectiveMode": 2}
							}
						},
						{
							"name": "Outer13",
							"from": [ 18.0, -0.64, 2.0 ], 
							"to": [ 21.0, 4.64, 5.0 ], 
							"rotationOrigin": [ 1.0, 2.0, 2.0 ],
							"rotationZ": 60.0,
							"faces": {
								"north": { "texture": "#brass", "uv": [ 0.0, 0.0, 3.0, 5.0 ], "reflectiveMode": 2},
								"east": { "texture": "#brass", "uv": [ 0.0, 0.0, 3.0, 5.0 ], "reflectiveMode": 2},
								"south": { "texture": "#brass", "uv": [ 0.0, 0.0, 3.0, 5.0 ], "reflectiveMode": 2},
								"west": { "texture": "#brass", "uv": [ 0.0, 0.0, 3.0, 5.0 ], "reflectiveMode": 2},
								"up": { "texture": "#brass", "uv": [ 0.0, 0.0, 3.0, 3.0 ], "reflectiveMode": 2},
								"down": { "texture": "#brass", "uv": [ 0.0, 0.0, 3.0, 3.0 ], "reflectiveMode": 2}
							}
						},
						{
							"name": "Outer12",
							"from": [ 18.0, -0.64, 2.0 ], 
							"to": [ 21.0, 4.64, 5.0 ], 
							"rotationOrigin": [ 1.0, 2.0, 2.0 ],
							"rotationZ": 45.0,
							"faces": {
								"north": { "texture": "#brass", "uv": [ 0.0, 0.0, 3.0, 5.0 ], "reflectiveMode": 2},
								"east": { "texture": "#brass", "uv": [ 0.0, 0.0, 3.0, 5.0 ], "reflectiveMode": 2},
								"south": { "texture": "#brass", "uv": [ 0.0, 0.0, 3.0, 5.0 ], "reflectiveMode": 2},
								"west": { "texture": "#brass", "uv": [ 0.0, 0.0, 3.0, 5.0 ], "reflectiveMode": 2},
								"up": { "texture": "#brass", "uv": [ 0.0, 0.0, 3.0, 3.0 ], "reflectiveMode": 2},
								"down": { "texture": "#brass", "uv": [ 0.0, 0.0, 3.0, 3.0 ], "reflectiveMode": 2}
							}
						},
						{
							"name": "Outer11",
							"from": [ 18.0, -0.64, 2.0 ], 
							"to": [ 21.0, 4.64, 5.0 ], 
							"rotationOrigin": [ 1.0, 2.0, 2.0 ],
							"rotationZ": 30.0,
							"faces": {
								"north": { "texture": "#brass", "uv": [ 0.0, 0.0, 3.0, 5.0 ], "reflectiveMode": 2},
								"east": { "texture": "#brass", "uv": [ 0.0, 0.0, 3.0, 5.0 ], "reflectiveMode": 2},
								"south": { "texture": "#brass", "uv": [ 0.0, 0.0, 3.0, 5.0 ], "reflectiveMode": 2},
								"west": { "texture": "#brass", "uv": [ 0.0, 0.0, 3.0, 5.0 ], "reflectiveMode": 2},
								"up": { "texture": "#brass", "uv": [ 0.0, 0.0, 3.0, 3.0 ], "reflectiveMode": 2},
								"down": { "texture": "#brass", "uv": [ 0.0, 0.0, 3.0, 3.0 ], "reflectiveMode": 2}
							}
						},
						{
							"name": "Outer10",
							"from": [ 18.0, -0.64, 2.0 ], 
							"to": [ 21.0, 4.64, 5.0 ], 
							"rotationOrigin": [ 1.0, 2.0, 2.0 ],
							"rotationZ": 15.0,
							"faces": {
								"north": { "texture": "#brass", "uv": [ 0.0, 0.0, 3.0, 5.0 ], "reflectiveMode": 2},
								"east": { "texture": "#brass", "uv": [ 0.0, 0.0, 3.0, 5.0 ], "reflectiveMode": 2},
								"south": { "texture": "#brass", "uv": [ 0.0, 0.0, 3.0, 5.0 ], "reflectiveMode": 2},
								"west": { "texture": "#brass", "uv": [ 0.0, 0.0, 3.0, 5.0 ], "reflectiveMode": 2},
								"up": { "texture": "#brass", "uv": [ 0.0, 0.0, 3.0, 3.0 ], "reflectiveMode": 2},
								"down": { "texture": "#brass", "uv": [ 0.0, 0.0, 3.0, 3.0 ], "reflectiveMode": 2}
							}
						},
						{
							"name": "Outer",
							"from": [ 18.0, -0.64, 2.0 ], 
							"to": [ 21.0, 4.64, 5.0 ], 
							"rotationOrigin": [ 1.0, 2.0, 2.0 ],
							"faces": {
								"north": { "texture": "#brass", "uv": [ 0.0, 0.0, 3.0, 5.0 ], "reflectiveMode": 2},
								"east": { "texture": "#brass", "uv": [ 0.0, 0.0, 3.0, 5.0 ], "reflectiveMode": 2},
								"south": { "texture": "#brass", "uv": [ 0.0, 0.0, 3.0, 5.0 ], "reflectiveMode": 2},
								"west": { "texture": "#brass", "uv": [ 0.0, 0.0, 3.0, 5.0 ], "reflectiveMode": 2},
								"up": { "texture": "#brass", "uv": [ 0.0, 0.0, 3.0, 3.0 ], "reflectiveMode": 2},
								"down": { "texture": "#brass", "uv": [ 0.0, 0.0, 3.0, 3.0 ], "reflectiveMode": 2}
							}
						}
					]
				},
				{
					"name": "OuterL",
					"from": [ 18.2, -0.64, 0.5 ], 
					"to": [ 20.8, 4.64, 4.5 ], 
					"rotationOrigin": [ 1.0, 2.0, 1.0 ],
					"faces": {
						"north": { "texture": "#lead", "uv": [ 0.0, 0.0, 2.5, 5.0 ], "reflectiveMode": 2},
						"east": { "texture": "#lead", "uv": [ 0.0, 0.0, 4.0, 5.0 ], "reflectiveMode": 2},
						"south": { "texture": "#lead", "uv": [ 0.0, 0.0, 2.5, 5.0 ], "reflectiveMode": 2},
						"west": { "texture": "#lead", "uv": [ 0.0, 0.0, 4.0, 5.0 ], "reflectiveMode": 2},
						"up": { "texture": "#lead", "uv": [ 0.0, 0.0, 2.5, 4.0 ], "reflectiveMode": 2},
						"down": { "texture": "#lead", "uv": [ 0.0, 0.0, 2.5, 4.0 ], "reflectiveMode": 2}
					},
					"children": [
						{
							"name": "OuterL43",
							"from": [ 0.0, 0.0, -0.01 ], 
							"to": [ 2.6, 5.28, 4.01 ], 
							"rotationOrigin": [ -17.2, 2.64, 0.5 ],
							"rotationZ": 15.0,
							"faces": {
								"north": { "texture": "#lead", "uv": [ 0.0, 0.0, 2.5, 5.0 ], "reflectiveMode": 2},
								"east": { "texture": "#lead", "uv": [ 0.0, 0.0, 4.0, 5.0 ], "reflectiveMode": 2},
								"south": { "texture": "#lead", "uv": [ 0.0, 0.0, 2.5, 5.0 ], "reflectiveMode": 2},
								"west": { "texture": "#lead", "uv": [ 0.0, 0.0, 4.0, 5.0 ], "reflectiveMode": 2},
								"up": { "texture": "#lead", "uv": [ 0.0, 0.0, 2.5, 4.0 ], "reflectiveMode": 2},
								"down": { "texture": "#lead", "uv": [ 0.0, 0.0, 2.5, 4.0 ], "reflectiveMode": 2}
							}
						},
						{
							"name": "OuterL44",
							"from": [ 0.0, 0.0, -0.01 ], 
							"to": [ 2.6, 5.28, 4.01 ], 
							"rotationOrigin": [ -17.2, 2.64, 0.5 ],
							"rotationZ": 45.0,
							"faces": {
								"north": { "texture": "#lead", "uv": [ 0.0, 0.0, 2.5, 5.0 ], "reflectiveMode": 2},
								"east": { "texture": "#lead", "uv": [ 0.0, 0.0, 4.0, 5.0 ], "reflectiveMode": 2},
								"south": { "texture": "#lead", "uv": [ 0.0, 0.0, 2.5, 5.0 ], "reflectiveMode": 2},
								"west": { "texture": "#lead", "uv": [ 0.0, 0.0, 4.0, 5.0 ], "reflectiveMode": 2},
								"up": { "texture": "#lead", "uv": [ 0.0, 0.0, 2.5, 4.0 ], "reflectiveMode": 2},
								"down": { "texture": "#lead", "uv": [ 0.0, 0.0, 2.5, 4.0 ], "reflectiveMode": 2}
							}
						},
						{
							"name": "OuterL45",
							"from": [ 0.0, 0.0, -0.01 ], 
							"to": [ 2.6, 5.28, 4.01 ], 
							"rotationOrigin": [ -17.2, 2.64, 0.5 ],
							"rotationZ": 75.0,
							"faces": {
								"north": { "texture": "#lead", "uv": [ 0.0, 0.0, 2.5, 5.0 ], "reflectiveMode": 2},
								"east": { "texture": "#lead", "uv": [ 0.0, 0.0, 4.0, 5.0 ], "reflectiveMode": 2},
								"south": { "texture": "#lead", "uv": [ 0.0, 0.0, 2.5, 5.0 ], "reflectiveMode": 2},
								"west": { "texture": "#lead", "uv": [ 0.0, 0.0, 4.0, 5.0 ], "reflectiveMode": 2},
								"up": { "texture": "#lead", "uv": [ 0.0, 0.0, 2.5, 4.0 ], "reflectiveMode": 2},
								"down": { "texture": "#lead", "uv": [ 0.0, 0.0, 2.5, 4.0 ], "reflectiveMode": 2}
							}
						},
						{
							"name": "OuterL46",
							"from": [ 0.0, 0.0, -0.01 ], 
							"to": [ 2.6, 5.28, 4.01 ], 
							"rotationOrigin": [ -17.2, 2.64, 0.5 ],
							"rotationZ": 105.0,
							"faces": {
								"north": { "texture": "#lead", "uv": [ 0.0, 0.0, 2.5, 5.0 ], "reflectiveMode": 2},
								"east": { "texture": "#lead", "uv": [ 0.0, 0.0, 4.0, 5.0 ], "reflectiveMode": 2},
								"south": { "texture": "#lead", "uv": [ 0.0, 0.0, 2.5, 5.0 ], "reflectiveMode": 2},
								"west": { "texture": "#lead", "uv": [ 0.0, 0.0, 4.0, 5.0 ], "reflectiveMode": 2},
								"up": { "texture": "#lead", "uv": [ 0.0, 0.0, 2.5, 4.0 ], "reflectiveMode": 2},
								"down": { "texture": "#lead", "uv": [ 0.0, 0.0, 2.5, 4.0 ], "reflectiveMode": 2}
							}
						},
						{
							"name": "OuterL47",
							"from": [ 0.0, 0.0, -0.01 ], 
							"to": [ 2.6, 5.28, 4.01 ], 
							"rotationOrigin": [ -17.2, 2.64, 0.5 ],
							"rotationZ": 135.0,
							"faces": {
								"north": { "texture": "#lead", "uv": [ 0.0, 0.0, 2.5, 5.0 ], "reflectiveMode": 2},
								"east": { "texture": "#lead", "uv": [ 0.0, 0.0, 4.0, 5.0 ], "reflectiveMode": 2},
								"south": { "texture": "#lead", "uv": [ 0.0, 0.0, 2.5, 5.0 ], "reflectiveMode": 2},
								"west": { "texture": "#lead", "uv": [ 0.0, 0.0, 4.0, 5.0 ], "reflectiveMode": 2},
								"up": { "texture": "#lead", "uv": [ 0.0, 0.0, 2.5, 4.0 ], "reflectiveMode": 2},
								"down": { "texture": "#lead", "uv": [ 0.0, 0.0, 2.5, 4.0 ], "reflectiveMode": 2}
							}
						},
						{
							"name": "OuterL48",
							"from": [ 0.0, 0.0, -0.01 ], 
							"to": [ 2.6, 5.28, 4.01 ], 
							"rotationOrigin": [ -17.2, 2.64, 0.5 ],
							"rotationZ": 165.0,
							"faces": {
								"north": { "texture": "#lead", "uv": [ 0.0, 0.0, 2.5, 5.0 ], "reflectiveMode": 2},
								"east": { "texture": "#lead", "uv": [ 0.0, 0.0, 4.0, 5.0 ], "reflectiveMode": 2},
								"south": { "texture": "#lead", "uv": [ 0.0, 0.0, 2.5, 5.0 ], "reflectiveMode": 2},
								"west": { "texture": "#lead", "uv": [ 0.0, 0.0, 4.0, 5.0 ], "reflectiveMode": 2},
								"up": { "texture": "#lead", "uv": [ 0.0, 0.0, 2.5, 4.0 ], "reflectiveMode": 2},
								"down": { "texture": "#lead", "uv": [ 0.0, 0.0, 2.5, 4.0 ], "reflectiveMode": 2}
							}
						},
						{
							"name": "OuterL49",
							"from": [ 0.0, 0.0, -0.01 ], 
							"to": [ 2.6, 5.28, 4.01 ], 
							"rotationOrigin": [ -17.2, 2.64, 0.5 ],
							"rotationZ": 195.0,
							"faces": {
								"north": { "texture": "#lead", "uv": [ 0.0, 0.0, 2.5, 5.0 ], "reflectiveMode": 2},
								"east": { "texture": "#lead", "uv": [ 0.0, 0.0, 4.0, 5.0 ], "reflectiveMode": 2},
								"south": { "texture": "#lead", "uv": [ 0.0, 0.0, 2.5, 5.0 ], "reflectiveMode": 2},
								"west": { "texture": "#lead", "uv": [ 0.0, 0.0, 4.0, 5.0 ], "reflectiveMode": 2},
								"up": { "texture": "#lead", "uv": [ 0.0, 0.0, 2.5, 4.0 ], "reflectiveMode": 2},
								"down": { "texture": "#lead", "uv": [ 0.0, 0.0, 2.5, 4.0 ], "reflectiveMode": 2}
							}
						},
						{
							"name": "OuterL50",
							"from": [ 0.0, 0.0, -0.01 ], 
							"to": [ 2.6, 5.28, 4.01 ], 
							"rotationOrigin": [ -17.2, 2.64, 0.5 ],
							"rotationZ": 225.0,
							"faces": {
								"north": { "texture": "#lead", "uv": [ 0.0, 0.0, 2.5, 5.0 ], "reflectiveMode": 2},
								"east": { "texture": "#lead", "uv": [ 0.0, 0.0, 4.0, 5.0 ], "reflectiveMode": 2},
								"south": { "texture": "#lead", "uv": [ 0.0, 0.0, 2.5, 5.0 ], "reflectiveMode": 2},
								"west": { "texture": "#lead", "uv": [ 0.0, 0.0, 4.0, 5.0 ], "reflectiveMode": 2},
								"up": { "texture": "#lead", "uv": [ 0.0, 0.0, 2.5, 4.0 ], "reflectiveMode": 2},
								"down": { "texture": "#lead", "uv": [ 0.0, 0.0, 2.5, 4.0 ], "reflectiveMode": 2}
							}
						},
						{
							"name": "OuterL51",
							"from": [ 0.0, 0.0, -0.01 ], 
							"to": [ 2.6, 5.28, 4.01 ], 
							"rotationOrigin": [ -17.2, 2.64, 0.5 ],
							"rotationZ": 255.0,
							"faces": {
								"north": { "texture": "#lead", "uv": [ 0.0, 0.0, 2.5, 5.0 ], "reflectiveMode": 2},
								"east": { "texture": "#lead", "uv": [ 0.0, 0.0, 4.0, 5.0 ], "reflectiveMode": 2},
								"south": { "texture": "#lead", "uv": [ 0.0, 0.0, 2.5, 5.0 ], "reflectiveMode": 2},
								"west": { "texture": "#lead", "uv": [ 0.0, 0.0, 4.0, 5.0 ], "reflectiveMode": 2},
								"up": { "texture": "#lead", "uv": [ 0.0, 0.0, 2.5, 4.0 ], "reflectiveMode": 2},
								"down": { "texture": "#lead", "uv": [ 0.0, 0.0, 2.5, 4.0 ], "reflectiveMode": 2}
							}
						},
						{
							"name": "OuterL52",
							"from": [ 0.0, 0.0, -0.01 ], 
							"to": [ 2.6, 5.28, 4.01 ], 
							"rotationOrigin": [ -17.2, 2.64, 0.5 ],
							"rotationZ": 285.0,
							"faces": {
								"north": { "texture": "#lead", "uv": [ 0.0, 0.0, 2.5, 5.0 ], "reflectiveMode": 2},
								"east": { "texture": "#lead", "uv": [ 0.0, 0.0, 4.0, 5.0 ], "reflectiveMode": 2},
								"south": { "texture": "#lead", "uv": [ 0.0, 0.0, 2.5, 5.0 ], "reflectiveMode": 2},
								"west": { "texture": "#lead", "uv": [ 0.0, 0.0, 4.0, 5.0 ], "reflectiveMode": 2},
								"up": { "texture": "#lead", "uv": [ 0.0, 0.0, 2.5, 4.0 ], "reflectiveMode": 2},
								"down": { "texture": "#lead", "uv": [ 0.0, 0.0, 2.5, 4.0 ], "reflectiveMode": 2}
							}
						},
						{
							"name": "OuterL53",
							"from": [ 0.0, 0.0, -0.01 ], 
							"to": [ 2.6, 5.28, 4.01 ], 
							"rotationOrigin": [ -17.2, 2.64, 0.5 ],
							"rotationZ": 315.0,
							"faces": {
								"north": { "texture": "#lead", "uv": [ 0.0, 0.0, 2.5, 5.0 ], "reflectiveMode": 2},
								"east": { "texture": "#lead", "uv": [ 0.0, 0.0, 4.0, 5.0 ], "reflectiveMode": 2},
								"south": { "texture": "#lead", "uv": [ 0.0, 0.0, 2.5, 5.0 ], "reflectiveMode": 2},
								"west": { "texture": "#lead", "uv": [ 0.0, 0.0, 4.0, 5.0 ], "reflectiveMode": 2},
								"up": { "texture": "#lead", "uv": [ 0.0, 0.0, 2.5, 4.0 ], "reflectiveMode": 2},
								"down": { "texture": "#lead", "uv": [ 0.0, 0.0, 2.5, 4.0 ], "reflectiveMode": 2}
							}
						},
						{
							"name": "OuterL54",
							"from": [ 0.0, 0.0, -0.01 ], 
							"to": [ 2.6, 5.28, 4.01 ], 
							"rotationOrigin": [ -17.2, 2.64, 0.5 ],
							"rotationZ": 345.0,
							"faces": {
								"north": { "texture": "#lead", "uv": [ 0.0, 0.0, 2.5, 5.0 ], "reflectiveMode": 2},
								"east": { "texture": "#lead", "uv": [ 0.0, 0.0, 4.0, 5.0 ], "reflectiveMode": 2},
								"south": { "texture": "#lead", "uv": [ 0.0, 0.0, 2.5, 5.0 ], "reflectiveMode": 2},
								"west": { "texture": "#lead", "uv": [ 0.0, 0.0, 4.0, 5.0 ], "reflectiveMode": 2},
								"up": { "texture": "#lead", "uv": [ 0.0, 0.0, 2.5, 4.0 ], "reflectiveMode": 2},
								"down": { "texture": "#lead", "uv": [ 0.0, 0.0, 2.5, 4.0 ], "reflectiveMode": 2}
							}
						},
						{
							"name": "OuterL55",
							"from": [ 0.0, 0.0, 0.0 ], 
							"to": [ 2.6, 5.28, 4.0 ], 
							"rotationOrigin": [ -17.2, 2.64, 0.5 ],
							"rotationZ": 30.0,
							"faces": {
								"north": { "texture": "#lead", "uv": [ 0.0, 0.0, 2.5, 5.0 ], "reflectiveMode": 2},
								"east": { "texture": "#lead", "uv": [ 0.0, 0.0, 4.0, 5.0 ], "reflectiveMode": 2},
								"south": { "texture": "#lead", "uv": [ 0.0, 0.0, 2.5, 5.0 ], "reflectiveMode": 2},
								"west": { "texture": "#lead", "uv": [ 0.0, 0.0, 4.0, 5.0 ], "reflectiveMode": 2},
								"up": { "texture": "#lead", "uv": [ 0.0, 0.0, 2.5, 4.0 ], "reflectiveMode": 2},
								"down": { "texture": "#lead", "uv": [ 0.0, 0.0, 2.5, 4.0 ], "reflectiveMode": 2}
							}
						},
						{
							"name": "OuterL56",
							"from": [ 0.0, 0.0, 0.0 ], 
							"to": [ 2.6, 5.28, 4.0 ], 
							"rotationOrigin": [ -17.2, 2.64, 0.5 ],
							"rotationZ": 60.0,
							"faces": {
								"north": { "texture": "#lead", "uv": [ 0.0, 0.0, 2.5, 5.0 ], "reflectiveMode": 2},
								"east": { "texture": "#lead", "uv": [ 0.0, 0.0, 4.0, 5.0 ], "reflectiveMode": 2},
								"south": { "texture": "#lead", "uv": [ 0.0, 0.0, 2.5, 5.0 ], "reflectiveMode": 2},
								"west": { "texture": "#lead", "uv": [ 0.0, 0.0, 4.0, 5.0 ], "reflectiveMode": 2},
								"up": { "texture": "#lead", "uv": [ 0.0, 0.0, 2.5, 4.0 ], "reflectiveMode": 2},
								"down": { "texture": "#lead", "uv": [ 0.0, 0.0, 2.5, 4.0 ], "reflectiveMode": 2}
							}
						},
						{
							"name": "OuterL57",
							"from": [ 0.0, 0.0, 0.0 ], 
							"to": [ 2.6, 5.28, 4.0 ], 
							"rotationOrigin": [ -17.2, 2.64, 0.5 ],
							"rotationZ": 90.0,
							"faces": {
								"north": { "texture": "#lead", "uv": [ 0.0, 0.0, 2.5, 5.0 ], "reflectiveMode": 2},
								"east": { "texture": "#lead", "uv": [ 0.0, 0.0, 4.0, 5.0 ], "reflectiveMode": 2},
								"south": { "texture": "#lead", "uv": [ 0.0, 0.0, 2.5, 5.0 ], "reflectiveMode": 2},
								"west": { "texture": "#lead", "uv": [ 0.0, 0.0, 4.0, 5.0 ], "reflectiveMode": 2},
								"up": { "texture": "#lead", "uv": [ 0.0, 0.0, 2.5, 4.0 ], "reflectiveMode": 2},
								"down": { "texture": "#lead", "uv": [ 0.0, 0.0, 2.5, 4.0 ], "reflectiveMode": 2}
							}
						},
						{
							"name": "OuterL58",
							"from": [ 0.0, 0.0, 0.0 ], 
							"to": [ 2.6, 5.28, 4.0 ], 
							"rotationOrigin": [ -17.2, 2.64, 0.5 ],
							"rotationZ": 120.0,
							"faces": {
								"north": { "texture": "#lead", "uv": [ 0.0, 0.0, 2.5, 5.0 ], "reflectiveMode": 2},
								"east": { "texture": "#lead", "uv": [ 0.0, 0.0, 4.0, 5.0 ], "reflectiveMode": 2},
								"south": { "texture": "#lead", "uv": [ 0.0, 0.0, 2.5, 5.0 ], "reflectiveMode": 2},
								"west": { "texture": "#lead", "uv": [ 0.0, 0.0, 4.0, 5.0 ], "reflectiveMode": 2},
								"up": { "texture": "#lead", "uv": [ 0.0, 0.0, 2.5, 4.0 ], "reflectiveMode": 2},
								"down": { "texture": "#lead", "uv": [ 0.0, 0.0, 2.5, 4.0 ], "reflectiveMode": 2}
							}
						},
						{
							"name": "OuterL59",
							"from": [ 0.0, 0.0, 0.0 ], 
							"to": [ 2.6, 5.28, 4.0 ], 
							"rotationOrigin": [ -17.2, 2.64, 0.5 ],
							"rotationZ": 150.0,
							"faces": {
								"north": { "texture": "#lead", "uv": [ 0.0, 0.0, 2.5, 5.0 ], "reflectiveMode": 2},
								"east": { "texture": "#lead", "uv": [ 0.0, 0.0, 4.0, 5.0 ], "reflectiveMode": 2},
								"south": { "texture": "#lead", "uv": [ 0.0, 0.0, 2.5, 5.0 ], "reflectiveMode": 2},
								"west": { "texture": "#lead", "uv": [ 0.0, 0.0, 4.0, 5.0 ], "reflectiveMode": 2},
								"up": { "texture": "#lead", "uv": [ 0.0, 0.0, 2.5, 4.0 ], "reflectiveMode": 2},
								"down": { "texture": "#lead", "uv": [ 0.0, 0.0, 2.5, 4.0 ], "reflectiveMode": 2}
							}
						},
						{
							"name": "OuterL60",
							"from": [ 0.0, 0.0, 0.0 ], 
							"to": [ 2.6, 5.28, 4.0 ], 
							"rotationOrigin": [ -17.2, 2.64, 0.5 ],
							"rotationZ": 180.0,
							"faces": {
								"north": { "texture": "#lead", "uv": [ 0.0, 0.0, 2.5, 5.0 ], "reflectiveMode": 2},
								"east": { "texture": "#lead", "uv": [ 0.0, 0.0, 4.0, 5.0 ], "reflectiveMode": 2},
								"south": { "texture": "#lead", "uv": [ 0.0, 0.0, 2.5, 5.0 ], "reflectiveMode": 2},
								"west": { "texture": "#lead", "uv": [ 0.0, 0.0, 4.0, 5.0 ], "reflectiveMode": 2},
								"up": { "texture": "#lead", "uv": [ 0.0, 0.0, 2.5, 4.0 ], "reflectiveMode": 2},
								"down": { "texture": "#lead", "uv": [ 0.0, 0.0, 2.5, 4.0 ], "reflectiveMode": 2}
							}
						},
						{
							"name": "OuterL61",
							"from": [ 0.0, 0.0, 0.0 ], 
							"to": [ 2.6, 5.28, 4.0 ], 
							"rotationOrigin": [ -17.2, 2.64, 0.5 ],
							"rotationZ": 210.0,
							"faces": {
								"north": { "texture": "#lead", "uv": [ 0.0, 0.0, 2.5, 5.0 ], "reflectiveMode": 2},
								"east": { "texture": "#lead", "uv": [ 0.0, 0.0, 4.0, 5.0 ], "reflectiveMode": 2},
								"south": { "texture": "#lead", "uv": [ 0.0, 0.0, 2.5, 5.0 ], "reflectiveMode": 2},
								"west": { "texture": "#lead", "uv": [ 0.0, 0.0, 4.0, 5.0 ], "reflectiveMode": 2},
								"up": { "texture": "#lead", "uv": [ 0.0, 0.0, 2.5, 4.0 ], "reflectiveMode": 2},
								"down": { "texture": "#lead", "uv": [ 0.0, 0.0, 2.5, 4.0 ], "reflectiveMode": 2}
							}
						},
						{
							"name": "OuterL62",
							"from": [ 0.0, 0.0, 0.0 ], 
							"to": [ 2.6, 5.28, 4.0 ], 
							"rotationOrigin": [ -17.2, 2.64, 0.5 ],
							"rotationZ": 240.0,
							"faces": {
								"north": { "texture": "#lead", "uv": [ 0.0, 0.0, 2.5, 5.0 ], "reflectiveMode": 2},
								"east": { "texture": "#lead", "uv": [ 0.0, 0.0, 4.0, 5.0 ], "reflectiveMode": 2},
								"south": { "texture": "#lead", "uv": [ 0.0, 0.0, 2.5, 5.0 ], "reflectiveMode": 2},
								"west": { "texture": "#lead", "uv": [ 0.0, 0.0, 4.0, 5.0 ], "reflectiveMode": 2},
								"up": { "texture": "#lead", "uv": [ 0.0, 0.0, 2.5, 4.0 ], "reflectiveMode": 2},
								"down": { "texture": "#lead", "uv": [ 0.0, 0.0, 2.5, 4.0 ], "reflectiveMode": 2}
							}
						},
						{
							"name": "OuterL63",
							"from": [ 0.0, 0.0, 0.0 ], 
							"to": [ 2.6, 5.28, 4.0 ], 
							"rotationOrigin": [ -17.2, 2.64, 0.5 ],
							"rotationZ": 270.0,
							"faces": {
								"north": { "texture": "#lead", "uv": [ 0.0, 0.0, 2.5, 5.0 ], "reflectiveMode": 2},
								"east": { "texture": "#lead", "uv": [ 0.0, 0.0, 4.0, 5.0 ], "reflectiveMode": 2},
								"south": { "texture": "#lead", "uv": [ 0.0, 0.0, 2.5, 5.0 ], "reflectiveMode": 2},
								"west": { "texture": "#lead", "uv": [ 0.0, 0.0, 4.0, 5.0 ], "reflectiveMode": 2},
								"up": { "texture": "#lead", "uv": [ 0.0, 0.0, 2.5, 4.0 ], "reflectiveMode": 2},
								"down": { "texture": "#lead", "uv": [ 0.0, 0.0, 2.5, 4.0 ], "reflectiveMode": 2}
							}
						},
						{
							"name": "OuterL64",
							"from": [ 0.0, 0.0, 0.0 ], 
							"to": [ 2.6, 5.28, 4.0 ], 
							"rotationOrigin": [ -17.2, 2.64, 0.5 ],
							"rotationZ": 300.0,
							"faces": {
								"north": { "texture": "#lead", "uv": [ 0.0, 0.0, 2.5, 5.0 ], "reflectiveMode": 2},
								"east": { "texture": "#lead", "uv": [ 0.0, 0.0, 4.0, 5.0 ], "reflectiveMode": 2},
								"south": { "texture": "#lead", "uv": [ 0.0, 0.0, 2.5, 5.0 ], "reflectiveMode": 2},
								"west": { "texture": "#lead", "uv": [ 0.0, 0.0, 4.0, 5.0 ], "reflectiveMode": 2},
								"up": { "texture": "#lead", "uv": [ 0.0, 0.0, 2.5, 4.0 ], "reflectiveMode": 2},
								"down": { "texture": "#lead", "uv": [ 0.0, 0.0, 2.5, 4.0 ], "reflectiveMode": 2}
							}
						},
						{
							"name": "OuterL65",
							"from": [ 0.0, 0.0, 0.0 ], 
							"to": [ 2.6, 5.28, 4.0 ], 
							"rotationOrigin": [ -17.2, 2.64, 0.5 ],
							"rotationZ": 330.0,
							"faces": {
								"north": { "texture": "#lead", "uv": [ 0.0, 0.0, 2.5, 5.0 ], "reflectiveMode": 2},
								"east": { "texture": "#lead", "uv": [ 0.0, 0.0, 4.0, 5.0 ], "reflectiveMode": 2},
								"south": { "texture": "#lead", "uv": [ 0.0, 0.0, 2.5, 5.0 ], "reflectiveMode": 2},
								"west": { "texture": "#lead", "uv": [ 0.0, 0.0, 4.0, 5.0 ], "reflectiveMode": 2},
								"up": { "texture": "#lead", "uv": [ 0.0, 0.0, 2.5, 4.0 ], "reflectiveMode": 2},
								"down": { "texture": "#lead", "uv": [ 0.0, 0.0, 2.5, 4.0 ], "reflectiveMode": 2}
							}
						}
					]
				}
			]
		},
		{
			"name": "Gear",
			"from": [ 8.0, 8.0, 7.0 ], 
			"to": [ 8.0, 8.0, 7.0 ], 
			"rotationOrigin": [ 8.0, 8.0, 7.5 ],
			"faces": {
				"north": { "texture": "#brass", "uv": [ 0.0, 0.0, 0.5, 0.5 ], "reflectiveMode": 2},
				"east": { "texture": "#brass", "uv": [ 0.0, 0.0, 0.5, 0.5 ], "reflectiveMode": 2},
				"south": { "texture": "#brass", "uv": [ 0.0, 0.0, 0.5, 0.5 ], "reflectiveMode": 2},
				"west": { "texture": "#brass", "uv": [ 0.0, 0.0, 0.5, 0.5 ], "reflectiveMode": 2},
				"up": { "texture": "#brass", "uv": [ 0.0, 0.0, 0.5, 0.5 ], "reflectiveMode": 2},
				"down": { "texture": "#brass", "uv": [ 0.0, 0.0, 0.5, 0.5 ], "reflectiveMode": 2}
			},
			"children": [
				{
					"name": "tooth",
					"from": [ 1.7, -0.25, -1.5 ], 
					"to": [ 3.3, 0.25, 0.5 ], 
					"faces": {
						"north": { "texture": "#brass", "uv": [ 6.5, 7.5, 8.0, 8.0 ], "reflectiveMode": 2},
						"east": { "texture": "#brass", "uv": [ 6.5, 5.5, 8.5, 6.0 ], "reflectiveMode": 2},
						"south": { "texture": "#brass", "uv": [ 6.0, 5.0, 7.5, 5.5 ], "reflectiveMode": 2},
						"west": { "texture": "#brass", "uv": [ 4.0, 4.0, 6.0, 4.5 ], "reflectiveMode": 2},
						"up": { "texture": "#brass", "uv": [ 6.5, 7.0, 8.0, 9.0 ], "reflectiveMode": 2},
						"down": { "texture": "#brass", "uv": [ 5.5, 6.0, 7.0, 8.0 ], "reflectiveMode": 2}
					}
				},
				{
					"name": "Body",
					"from": [ -2.0, -2.0, -1.49 ], 
					"to": [ 2.0, 2.0, 0.49 ], 
					"rotationOrigin": [ -2.0, -2.0, -1.0 ],
					"faces": {
						"north": { "texture": "#brass", "uv": [ 9.0, 6.5, 13.0, 10.5 ], "reflectiveMode": 2},
						"east": { "texture": "#brass", "uv": [ 10.0, 6.0, 11.5, 10.0 ], "reflectiveMode": 2},
						"south": { "texture": "#brass", "uv": [ 8.5, 6.5, 12.5, 10.5 ], "reflectiveMode": 2},
						"west": { "texture": "#brass", "uv": [ 6.5, 4.5, 8.0, 8.5 ], "reflectiveMode": 2},
						"up": { "texture": "#brass", "uv": [ 6.5, 6.0, 10.5, 7.5 ], "reflectiveMode": 2},
						"down": { "texture": "#brass", "uv": [ 6.5, 7.5, 10.5, 9.0 ], "reflectiveMode": 2}
					}
				},
				{
					"name": "tooth5",
					"from": [ 1.7, -0.25, -1.5 ], 
					"to": [ 3.3, 0.25, 0.5 ], 
					"rotationOrigin": [ 0.0, 0.0, 0.0 ],
					"rotationZ": 22.5,
					"faces": {
						"north": { "texture": "#brass", "uv": [ 6.0, 5.5, 7.5, 6.0 ], "reflectiveMode": 2},
						"east": { "texture": "#brass", "uv": [ 5.5, 4.0, 7.5, 4.5 ], "reflectiveMode": 2},
						"south": { "texture": "#brass", "uv": [ 6.5, 5.5, 8.0, 6.0 ], "reflectiveMode": 2},
						"west": { "texture": "#brass", "uv": [ 5.5, 4.5, 7.5, 5.0 ], "reflectiveMode": 2},
						"up": { "texture": "#brass", "uv": [ 5.5, 8.5, 7.0, 10.5 ], "reflectiveMode": 2},
						"down": { "texture": "#brass", "uv": [ 5.0, 3.0, 6.5, 5.0 ], "reflectiveMode": 2}
					}
				},
				{
					"name": "tooth6",
					"from": [ 1.7, -0.25, -1.5 ], 
					"to": [ 3.3, 0.25, 0.5 ], 
					"rotationOrigin": [ 0.0, 0.0, 0.0 ],
					"rotationZ": 45.0,
					"faces": {
						"north": { "texture": "#brass", "uv": [ 7.0, 4.0, 8.5, 4.5 ], "reflectiveMode": 2},
						"east": { "texture": "#brass", "uv": [ 9.0, 6.0, 11.0, 6.5 ], "reflectiveMode": 2},
						"south": { "texture": "#brass", "uv": [ 8.0, 6.5, 9.5, 7.0 ], "reflectiveMode": 2},
						"west": { "texture": "#brass", "uv": [ 5.0, 4.0, 7.0, 4.5 ], "reflectiveMode": 2},
						"up": { "texture": "#brass", "uv": [ 11.0, 5.0, 12.5, 7.0 ], "reflectiveMode": 2},
						"down": { "texture": "#brass", "uv": [ 9.5, 4.5, 11.0, 6.5 ], "reflectiveMode": 2}
					}
				},
				{
					"name": "tooth7",
					"from": [ 1.7, -0.25, -1.5 ], 
					"to": [ 3.3, 0.25, 0.5 ], 
					"rotationOrigin": [ 0.0, 0.0, 0.0 ],
					"rotationZ": 67.5,
					"faces": {
						"north": { "texture": "#brass", "uv": [ 8.5, 9.0, 10.0, 9.5 ], "reflectiveMode": 2},
						"east": { "texture": "#brass", "uv": [ 7.5, 8.0, 9.5, 8.5 ], "reflectiveMode": 2},
						"south": { "texture": "#brass", "uv": [ 3.0, 7.0, 4.5, 7.5 ], "reflectiveMode": 2},
						"west": { "texture": "#brass", "uv": [ 11.0, 7.5, 13.0, 8.0 ], "reflectiveMode": 2},
						"up": { "texture": "#brass", "uv": [ 9.0, 5.0, 10.5, 7.0 ], "reflectiveMode": 2},
						"down": { "texture": "#brass", "uv": [ 9.5, 7.5, 11.0, 9.5 ], "reflectiveMode": 2}
					}
				},
				{
					"name": "tooth8",
					"from": [ 1.7, -0.25, -1.5 ], 
					"to": [ 3.3, 0.25, 0.5 ], 
					"rotationOrigin": [ 0.0, 0.0, 0.0 ],
					"rotationZ": 90.0,
					"faces": {
						"north": { "texture": "#brass", "uv": [ 1.5, 5.0, 3.0, 5.5 ], "reflectiveMode": 2},
						"east": { "texture": "#brass", "uv": [ 7.5, 5.0, 9.5, 5.5 ], "reflectiveMode": 2},
						"south": { "texture": "#brass", "uv": [ 6.0, 7.0, 7.5, 7.5 ], "reflectiveMode": 2},
						"west": { "texture": "#brass", "uv": [ 2.5, 7.0, 4.5, 7.5 ], "reflectiveMode": 2},
						"up": { "texture": "#brass", "uv": [ 11.0, 8.5, 12.5, 10.5 ], "reflectiveMode": 2},
						"down": { "texture": "#brass", "uv": [ 7.5, 4.5, 9.0, 6.5 ], "reflectiveMode": 2}
					}
				},
				{
					"name": "tooth9",
					"from": [ 1.7, -0.25, -1.5 ], 
					"to": [ 3.3, 0.25, 0.5 ], 
					"rotationOrigin": [ 0.0, 0.0, 0.0 ],
					"rotationZ": 112.5,
					"faces": {
						"north": { "texture": "#brass", "uv": [ 6.5, 9.0, 8.0, 9.5 ], "reflectiveMode": 2},
						"east": { "texture": "#brass", "uv": [ 7.0, 8.5, 9.0, 9.0 ], "reflectiveMode": 2},
						"south": { "texture": "#brass", "uv": [ 3.5, 7.0, 5.0, 7.5 ], "reflectiveMode": 2},
						"west": { "texture": "#brass", "uv": [ 12.0, 5.5, 14.0, 6.0 ], "reflectiveMode": 2},
						"up": { "texture": "#brass", "uv": [ 3.5, 6.5, 5.0, 8.5 ], "reflectiveMode": 2},
						"down": { "texture": "#brass", "uv": [ 5.0, 6.0, 6.5, 8.0 ], "reflectiveMode": 2}
					}
				},
				{
					"name": "tooth10",
					"from": [ 1.7, -0.25, -1.5 ], 
					"to": [ 3.3, 0.25, 0.5 ], 
					"rotationOrigin": [ 0.0, 0.0, 0.0 ],
					"rotationZ": 135.0,
					"faces": {
						"north": { "texture": "#brass", "uv": [ 6.5, 4.0, 8.0, 4.5 ], "reflectiveMode": 2},
						"east": { "texture": "#brass", "uv": [ 9.0, 4.5, 11.0, 5.0 ], "reflectiveMode": 2},
						"south": { "texture": "#brass", "uv": [ 4.0, 4.0, 5.5, 4.5 ], "reflectiveMode": 2},
						"west": { "texture": "#brass", "uv": [ 7.0, 13.0, 9.0, 13.5 ], "reflectiveMode": 2},
						"up": { "texture": "#brass", "uv": [ 5.0, 4.0, 6.5, 6.0 ], "reflectiveMode": 2},
						"down": { "texture": "#brass", "uv": [ 5.0, 5.0, 6.5, 7.0 ], "reflectiveMode": 2}
					}
				},
				{
					"name": "tooth11",
					"from": [ 1.7, -0.25, -1.5 ], 
					"to": [ 3.3, 0.25, 0.5 ], 
					"rotationOrigin": [ 0.0, 0.0, 0.0 ],
					"rotationZ": 157.5,
					"faces": {
						"north": { "texture": "#brass", "uv": [ 9.0, 10.0, 10.5, 10.5 ], "reflectiveMode": 2},
						"east": { "texture": "#brass", "uv": [ 3.5, 8.0, 5.5, 8.5 ], "reflectiveMode": 2},
						"south": { "texture": "#brass", "uv": [ 3.5, 8.5, 5.0, 9.0 ], "reflectiveMode": 2},
						"west": { "texture": "#brass", "uv": [ 4.0, 8.0, 6.0, 8.5 ], "reflectiveMode": 2},
						"up": { "texture": "#brass", "uv": [ 4.0, 9.5, 5.5, 11.5 ], "reflectiveMode": 2},
						"down": { "texture": "#brass", "uv": [ 6.5, 7.0, 8.0, 9.0 ], "reflectiveMode": 2}
					}
				},
				{
					"name": "tooth12",
					"from": [ 1.7, -0.25, -1.5 ], 
					"to": [ 3.3, 0.25, 0.5 ], 
					"rotationOrigin": [ 0.0, 0.0, 0.0 ],
					"rotationZ": 180.0,
					"faces": {
						"north": { "texture": "#brass", "uv": [ 11.5, 6.5, 13.0, 7.0 ], "reflectiveMode": 2},
						"east": { "texture": "#brass", "uv": [ 6.5, 9.0, 8.5, 9.5 ], "reflectiveMode": 2},
						"south": { "texture": "#brass", "uv": [ 10.0, 3.0, 11.5, 3.5 ], "reflectiveMode": 2},
						"west": { "texture": "#brass", "uv": [ 0.5, 14.5, 2.5, 15.0 ], "reflectiveMode": 2},
						"up": { "texture": "#brass", "uv": [ 7.0, 5.5, 8.5, 7.5 ], "reflectiveMode": 2},
						"down": { "texture": "#brass", "uv": [ 11.0, 5.5, 12.5, 7.5 ], "reflectiveMode": 2}
					}
				},
				{
					"name": "tooth13",
					"from": [ 1.7, -0.25, -1.5 ], 
					"to": [ 3.3, 0.25, 0.5 ], 
					"rotationOrigin": [ 0.0, 0.0, 0.0 ],
					"rotationZ": -157.5,
					"faces": {
						"north": { "texture": "#brass", "uv": [ 8.5, 10.0, 10.0, 10.5 ], "reflectiveMode": 2},
						"east": { "texture": "#brass", "uv": [ 1.0, 4.0, 3.0, 4.5 ], "reflectiveMode": 2},
						"south": { "texture": "#brass", "uv": [ 5.5, 0.5, 7.0, 1.0 ], "reflectiveMode": 2},
						"west": { "texture": "#brass", "uv": [ 9.5, 8.0, 11.5, 8.5 ], "reflectiveMode": 2},
						"up": { "texture": "#brass", "uv": [ 7.0, 7.5, 8.5, 9.5 ], "reflectiveMode": 2},
						"down": { "texture": "#brass", "uv": [ 9.5, 6.0, 11.0, 8.0 ], "reflectiveMode": 2}
					}
				},
				{
					"name": "tooth14",
					"from": [ 1.7, -0.25, -1.5 ], 
					"to": [ 3.3, 0.25, 0.5 ], 
					"rotationOrigin": [ 0.0, 0.0, 0.0 ],
					"rotationZ": -135.0,
					"faces": {
						"north": { "texture": "#brass", "uv": [ 5.5, 6.5, 7.0, 7.0 ], "reflectiveMode": 2},
						"east": { "texture": "#brass", "uv": [ 7.5, 7.0, 9.5, 7.5 ], "reflectiveMode": 2},
						"south": { "texture": "#brass", "uv": [ 8.5, 7.5, 10.0, 8.0 ], "reflectiveMode": 2},
						"west": { "texture": "#brass", "uv": [ 4.0, 9.5, 6.0, 10.0 ], "reflectiveMode": 2},
						"up": { "texture": "#brass", "uv": [ 4.0, 9.0, 5.5, 11.0 ], "reflectiveMode": 2},
						"down": { "texture": "#brass", "uv": [ 7.0, 7.0, 8.5, 9.0 ], "reflectiveMode": 2}
					}
				},
				{
					"name": "tooth15",
					"from": [ 1.7, -0.25, -1.5 ], 
					"to": [ 3.3, 0.25, 0.5 ], 
					"rotationOrigin": [ 0.0, 0.0, 0.0 ],
					"rotationZ": -112.5,
					"faces": {
						"north": { "texture": "#brass", "uv": [ 3.5, 9.5, 5.0, 10.0 ], "reflectiveMode": 2},
						"east": { "texture": "#brass", "uv": [ 6.5, 7.5, 8.5, 8.0 ], "reflectiveMode": 2},
						"south": { "texture": "#brass", "uv": [ 10.5, 10.0, 12.0, 10.5 ], "reflectiveMode": 2},
						"west": { "texture": "#brass", "uv": [ 8.5, 9.0, 10.5, 9.5 ], "reflectiveMode": 2},
						"up": { "texture": "#brass", "uv": [ 6.5, 10.0, 8.0, 12.0 ], "reflectiveMode": 2},
						"down": { "texture": "#brass", "uv": [ 6.0, 6.5, 7.5, 8.5 ], "reflectiveMode": 2}
					}
				},
				{
					"name": "tooth16",
					"from": [ 1.7, -0.25, -1.5 ], 
					"to": [ 3.3, 0.25, 0.5 ], 
					"rotationOrigin": [ 0.0, 0.0, 0.0 ],
					"rotationZ": -90.0,
					"faces": {
						"north": { "texture": "#brass", "uv": [ 8.0, 10.0, 9.5, 10.5 ], "reflectiveMode": 2},
						"east": { "texture": "#brass", "uv": [ 7.5, 4.5, 9.5, 5.0 ], "reflectiveMode": 2},
						"south": { "texture": "#brass", "uv": [ 6.5, 6.5, 8.0, 7.0 ], "reflectiveMode": 2},
						"west": { "texture": "#brass", "uv": [ 6.0, 9.0, 8.0, 9.5 ], "reflectiveMode": 2},
						"up": { "texture": "#brass", "uv": [ 8.5, 4.5, 10.0, 6.5 ], "reflectiveMode": 2},
						"down": { "texture": "#brass", "uv": [ 10.5, 3.0, 12.0, 5.0 ], "reflectiveMode": 2}
					}
				},
				{
					"name": "tooth17",
					"from": [ 1.7, -0.25, -1.5 ], 
					"to": [ 3.3, 0.25, 0.5 ], 
					"rotationOrigin": [ 0.0, 0.0, 0.0 ],
					"rotationZ": -67.5,
					"faces": {
						"north": { "texture": "#brass", "uv": [ 3.5, 5.5, 5.0, 6.0 ], "reflectiveMode": 2},
						"east": { "texture": "#brass", "uv": [ 11.5, 8.0, 13.5, 8.5 ], "reflectiveMode": 2},
						"south": { "texture": "#brass", "uv": [ 8.0, 7.5, 9.5, 8.0 ], "reflectiveMode": 2},
						"west": { "texture": "#brass", "uv": [ 6.0, 6.0, 8.0, 6.5 ], "reflectiveMode": 2},
						"up": { "texture": "#brass", "uv": [ 8.0, 11.0, 9.5, 13.0 ], "reflectiveMode": 2},
						"down": { "texture": "#brass", "uv": [ 7.0, 6.5, 8.5, 8.5 ], "reflectiveMode": 2}
					}
				},
				{
					"name": "tooth18",
					"from": [ 1.7, -0.25, -1.5 ], 
					"to": [ 3.3, 0.25, 0.5 ], 
					"rotationOrigin": [ 0.0, 0.0, 0.0 ],
					"rotationZ": -45.0,
					"faces": {
						"north": { "texture": "#brass", "uv": [ 7.0, 5.5, 8.5, 6.0 ], "reflectiveMode": 2},
						"east": { "texture": "#brass", "uv": [ 6.0, 6.0, 8.0, 6.5 ], "reflectiveMode": 2},
						"south": { "texture": "#brass", "uv": [ 1.0, 5.5, 2.5, 6.0 ], "reflectiveMode": 2},
						"west": { "texture": "#brass", "uv": [ 5.5, 9.0, 7.5, 9.5 ], "reflectiveMode": 2},
						"up": { "texture": "#brass", "uv": [ 10.0, 8.0, 11.5, 10.0 ], "reflectiveMode": 2},
						"down": { "texture": "#brass", "uv": [ 6.0, 4.0, 7.5, 6.0 ], "reflectiveMode": 2}
					}
				},
				{
					"name": "tooth19",
					"from": [ 1.7, -0.25, -1.5 ], 
					"to": [ 3.3, 0.25, 0.5 ], 
					"rotationOrigin": [ 0.0, 0.0, 0.0 ],
					"rotationZ": -22.5,
					"faces": {
						"north": { "texture": "#brass", "uv": [ 4.5, 5.5, 6.0, 6.0 ], "reflectiveMode": 2},
						"east": { "texture": "#brass", "uv": [ 6.5, 4.0, 8.5, 4.5 ], "reflectiveMode": 2},
						"south": { "texture": "#brass", "uv": [ 6.5, 6.5, 8.0, 7.0 ], "reflectiveMode": 2},
						"west": { "texture": "#brass", "uv": [ 4.0, 7.5, 6.0, 8.0 ], "reflectiveMode": 2},
						"up": { "texture": "#brass", "uv": [ 8.0, 8.5, 9.5, 10.5 ], "reflectiveMode": 2},
						"down": { "texture": "#brass", "uv": [ 8.0, 6.0, 9.5, 8.0 ], "reflectiveMode": 2}
					}
				},
				{
					"name": "innertooth",
					"from": [ 1.7, -0.3, -1.51 ], 
					"to": [ 2.8, 0.3, 0.51 ], 
					"rotationOrigin": [ 0.0, 0.0, 0.0 ],
					"rotationZ": 11.25,
					"faces": {
						"north": { "texture": "#brass", "uv": [ 4.5, 6.0, 5.5, 6.5 ], "reflectiveMode": 2},
						"east": { "texture": "#brass", "uv": [ 3.5, 3.5, 5.5, 4.0 ], "reflectiveMode": 2},
						"south": { "texture": "#brass", "uv": [ 6.5, 5.0, 7.5, 5.5 ], "reflectiveMode": 2},
						"west": { "texture": "#brass", "uv": [ 7.0, 8.0, 9.0, 8.5 ], "reflectiveMode": 2},
						"up": { "texture": "#brass", "uv": [ 4.5, 5.5, 5.5, 7.5 ], "reflectiveMode": 2},
						"down": { "texture": "#brass", "uv": [ 5.0, 4.5, 6.0, 6.5 ], "reflectiveMode": 2}
					},
					"children": [
						{
							"name": "innertooth21",
							"from": [ 0.0, 0.0, 0.0 ], 
							"to": [ 1.1, 0.6, 2.02 ], 
							"rotationOrigin": [ -1.7, 0.3, 1.51 ],
							"rotationZ": 22.5,
							"faces": {
								"north": { "texture": "#brass", "uv": [ 5.5, 8.0, 6.5, 8.5 ], "reflectiveMode": 2},
								"east": { "texture": "#brass", "uv": [ 7.5, 7.5, 9.5, 8.0 ], "reflectiveMode": 2},
								"south": { "texture": "#brass", "uv": [ 7.0, 6.5, 8.0, 7.0 ], "reflectiveMode": 2},
								"west": { "texture": "#brass", "uv": [ 5.0, 6.5, 7.0, 7.0 ], "reflectiveMode": 2},
								"up": { "texture": "#brass", "uv": [ 8.0, 11.5, 9.0, 13.5 ], "reflectiveMode": 2},
								"down": { "texture": "#brass", "uv": [ 13.0, 7.0, 14.0, 9.0 ], "reflectiveMode": 2}
							}
						},
						{
							"name": "innertooth23",
							"from": [ 0.0, 0.0, 0.0 ], 
							"to": [ 1.1, 0.6, 2.02 ], 
							"rotationOrigin": [ -1.7, 0.3, 1.51 ],
							"rotationZ": 67.5,
							"faces": {
								"north": { "texture": "#brass", "uv": [ 6.5, 9.5, 7.5, 10.0 ], "reflectiveMode": 2},
								"east": { "texture": "#brass", "uv": [ 5.0, 5.5, 7.0, 6.0 ], "reflectiveMode": 2},
								"south": { "texture": "#brass", "uv": [ 5.0, 8.5, 6.0, 9.0 ], "reflectiveMode": 2},
								"west": { "texture": "#brass", "uv": [ 9.0, 4.5, 11.0, 5.0 ], "reflectiveMode": 2},
								"up": { "texture": "#brass", "uv": [ 6.5, 7.5, 7.5, 9.5 ], "reflectiveMode": 2},
								"down": { "texture": "#brass", "uv": [ 9.0, 9.0, 10.0, 11.0 ], "reflectiveMode": 2}
							}
						},
						{
							"name": "innertooth22",
							"from": [ 0.0, 0.0, 0.0 ], 
							"to": [ 1.1, 0.6, 2.02 ], 
							"rotationOrigin": [ -1.7, 0.3, 1.51 ],
							"rotationZ": 45.0,
							"faces": {
								"north": { "texture": "#brass", "uv": [ 14.0, 8.0, 15.0, 8.5 ], "reflectiveMode": 2},
								"east": { "texture": "#brass", "uv": [ 7.5, 12.0, 9.5, 12.5 ], "reflectiveMode": 2},
								"south": { "texture": "#brass", "uv": [ 6.5, 5.5, 7.5, 6.0 ], "reflectiveMode": 2},
								"west": { "texture": "#brass", "uv": [ 6.5, 4.5, 8.5, 5.0 ], "reflectiveMode": 2},
								"up": { "texture": "#brass", "uv": [ 6.0, 6.0, 7.0, 8.0 ], "reflectiveMode": 2},
								"down": { "texture": "#brass", "uv": [ 7.0, 5.5, 8.0, 7.5 ], "reflectiveMode": 2}
							}
						},
						{
							"name": "innertooth24",
							"from": [ 0.0, 0.0, 0.0 ], 
							"to": [ 1.1, 0.6, 2.02 ], 
							"rotationOrigin": [ -1.7, 0.3, 1.51 ],
							"rotationZ": 90.0,
							"faces": {
								"north": { "texture": "#brass", "uv": [ 4.5, 4.0, 5.5, 4.5 ], "reflectiveMode": 2},
								"east": { "texture": "#brass", "uv": [ 4.5, 3.5, 6.5, 4.0 ], "reflectiveMode": 2},
								"south": { "texture": "#brass", "uv": [ 10.5, 6.5, 11.5, 7.0 ], "reflectiveMode": 2},
								"west": { "texture": "#brass", "uv": [ 6.5, 5.5, 8.5, 6.0 ], "reflectiveMode": 2},
								"up": { "texture": "#brass", "uv": [ 9.0, 6.5, 10.0, 8.5 ], "reflectiveMode": 2},
								"down": { "texture": "#brass", "uv": [ 6.5, 5.0, 7.5, 7.0 ], "reflectiveMode": 2}
							}
						},
						{
							"name": "innertooth25",
							"from": [ 0.0, 0.0, 0.0 ], 
							"to": [ 1.1, 0.6, 2.02 ], 
							"rotationOrigin": [ -1.7, 0.3, 1.51 ],
							"rotationZ": 112.5,
							"faces": {
								"north": { "texture": "#brass", "uv": [ 7.0, 7.0, 8.0, 7.5 ], "reflectiveMode": 2},
								"east": { "texture": "#brass", "uv": [ 7.0, 7.5, 9.0, 8.0 ], "reflectiveMode": 2},
								"south": { "texture": "#brass", "uv": [ 5.5, 5.5, 6.5, 6.0 ], "reflectiveMode": 2},
								"west": { "texture": "#brass", "uv": [ 7.5, 7.0, 9.5, 7.5 ], "reflectiveMode": 2},
								"up": { "texture": "#brass", "uv": [ 8.0, 6.5, 9.0, 8.5 ], "reflectiveMode": 2},
								"down": { "texture": "#brass", "uv": [ 10.0, 7.5, 11.0, 9.5 ], "reflectiveMode": 2}
							}
						},
						{
							"name": "innertooth26",
							"from": [ 0.0, 0.0, 0.0 ], 
							"to": [ 1.1, 0.6, 2.02 ], 
							"rotationOrigin": [ -1.7, 0.3, 1.51 ],
							"rotationZ": 135.0,
							"faces": {
								"north": { "texture": "#brass", "uv": [ 9.5, 5.0, 10.5, 5.5 ], "reflectiveMode": 2},
								"east": { "texture": "#brass", "uv": [ 9.5, 5.5, 11.5, 6.0 ], "reflectiveMode": 2},
								"south": { "texture": "#brass", "uv": [ 8.5, 8.5, 9.5, 9.0 ], "reflectiveMode": 2},
								"west": { "texture": "#brass", "uv": [ 10.5, 10.5, 12.5, 11.0 ], "reflectiveMode": 2},
								"up": { "texture": "#brass", "uv": [ 10.0, 8.0, 11.0, 10.0 ], "reflectiveMode": 2},
								"down": { "texture": "#brass", "uv": [ 12.5, 8.5, 13.5, 10.5 ], "reflectiveMode": 2}
							}
						},
						{
							"name": "innertooth27",
							"from": [ 0.0, 0.0, 0.0 ], 
							"to": [ 1.1, 0.6, 2.02 ], 
							"rotationOrigin": [ -1.7, 0.3, 1.51 ],
							"rotationZ": 157.5,
							"faces": {
								"north": { "texture": "#brass", "uv": [ 6.5, 5.5, 7.5, 6.0 ], "reflectiveMode": 2},
								"east": { "texture": "#brass", "uv": [ 6.5, 8.0, 8.5, 8.5 ], "reflectiveMode": 2},
								"south": { "texture": "#brass", "uv": [ 6.0, 7.0, 7.0, 7.5 ], "reflectiveMode": 2},
								"west": { "texture": "#brass", "uv": [ 10.0, 5.0, 12.0, 5.5 ], "reflectiveMode": 2},
								"up": { "texture": "#brass", "uv": [ 9.0, 8.5, 10.0, 10.5 ], "reflectiveMode": 2},
								"down": { "texture": "#brass", "uv": [ 8.5, 8.5, 9.5, 10.5 ], "reflectiveMode": 2}
							}
						},
						{
							"name": "innertooth28",
							"from": [ 0.0, 0.0, 0.0 ], 
							"to": [ 1.1, 0.6, 2.02 ], 
							"rotationOrigin": [ -1.7, 0.3, 1.51 ],
							"rotationZ": 180.0,
							"faces": {
								"north": { "texture": "#brass", "uv": [ 8.0, 7.0, 9.0, 7.5 ], "reflectiveMode": 2},
								"east": { "texture": "#brass", "uv": [ 9.0, 6.5, 11.0, 7.0 ], "reflectiveMode": 2},
								"south": { "texture": "#brass", "uv": [ 6.5, 7.0, 7.5, 7.5 ], "reflectiveMode": 2},
								"west": { "texture": "#brass", "uv": [ 8.0, 8.0, 10.0, 8.5 ], "reflectiveMode": 2},
								"up": { "texture": "#brass", "uv": [ 7.5, 8.0, 8.5, 10.0 ], "reflectiveMode": 2},
								"down": { "texture": "#brass", "uv": [ 6.5, 7.0, 7.5, 9.0 ], "reflectiveMode": 2}
							}
						},
						{
							"name": "innertooth29",
							"from": [ 0.0, 0.0, 0.0 ], 
							"to": [ 1.1, 0.6, 2.02 ], 
							"rotationOrigin": [ -1.7, 0.3, 1.51 ],
							"rotationZ": -22.5,
							"faces": {
								"north": { "texture": "#brass", "uv": [ 8.0, 7.5, 9.0, 8.0 ], "reflectiveMode": 2},
								"east": { "texture": "#brass", "uv": [ 7.0, 7.0, 9.0, 7.5 ], "reflectiveMode": 2},
								"south": { "texture": "#brass", "uv": [ 7.5, 7.5, 8.5, 8.0 ], "reflectiveMode": 2},
								"west": { "texture": "#brass", "uv": [ 9.5, 9.0, 11.5, 9.5 ], "reflectiveMode": 2},
								"up": { "texture": "#brass", "uv": [ 5.0, 7.5, 6.0, 9.5 ], "reflectiveMode": 2},
								"down": { "texture": "#brass", "uv": [ 7.5, 7.0, 8.5, 9.0 ], "reflectiveMode": 2}
							}
						},
						{
							"name": "innertooth30",
							"from": [ 0.0, 0.0, 0.0 ], 
							"to": [ 1.1, 0.6, 2.02 ], 
							"rotationOrigin": [ -1.7, 0.3, 1.51 ],
							"rotationZ": -45.0,
							"faces": {
								"north": { "texture": "#brass", "uv": [ 6.5, 6.0, 7.5, 6.5 ], "reflectiveMode": 2},
								"east": { "texture": "#brass", "uv": [ 7.5, 7.5, 9.5, 8.0 ], "reflectiveMode": 2},
								"south": { "texture": "#brass", "uv": [ 7.5, 7.0, 8.5, 7.5 ], "reflectiveMode": 2},
								"west": { "texture": "#brass", "uv": [ 8.0, 7.5, 10.0, 8.0 ], "reflectiveMode": 2},
								"up": { "texture": "#brass", "uv": [ 7.5, 7.5, 8.5, 9.5 ], "reflectiveMode": 2},
								"down": { "texture": "#brass", "uv": [ 7.5, 6.0, 8.5, 8.0 ], "reflectiveMode": 2}
							}
						},
						{
							"name": "innertooth31",
							"from": [ 0.0, 0.0, 0.0 ], 
							"to": [ 1.1, 0.6, 2.02 ], 
							"rotationOrigin": [ -1.7, 0.3, 1.51 ],
							"rotationZ": -67.5,
							"faces": {
								"north": { "texture": "#brass", "uv": [ 8.0, 7.5, 9.0, 8.0 ], "reflectiveMode": 2},
								"east": { "texture": "#brass", "uv": [ 8.0, 7.5, 10.0, 8.0 ], "reflectiveMode": 2},
								"south": { "texture": "#brass", "uv": [ 8.0, 7.0, 9.0, 7.5 ], "reflectiveMode": 2},
								"west": { "texture": "#brass", "uv": [ 6.0, 5.5, 8.0, 6.0 ], "reflectiveMode": 2},
								"up": { "texture": "#brass", "uv": [ 8.0, 7.5, 9.0, 9.5 ], "reflectiveMode": 2},
								"down": { "texture": "#brass", "uv": [ 7.5, 7.5, 8.5, 9.5 ], "reflectiveMode": 2}
							}
						},
						{
							"name": "innertooth32",
							"from": [ 0.0, 0.0, 0.0 ], 
							"to": [ 1.1, 0.6, 2.02 ], 
							"rotationOrigin": [ -1.7, 0.3, 1.51 ],
							"rotationZ": -90.0,
							"faces": {
								"north": { "texture": "#brass", "uv": [ 12.5, 7.0, 13.5, 7.5 ], "reflectiveMode": 2},
								"east": { "texture": "#brass", "uv": [ 13.0, 6.0, 15.0, 6.5 ], "reflectiveMode": 2},
								"south": { "texture": "#brass", "uv": [ 8.5, 7.5, 9.5, 8.0 ], "reflectiveMode": 2},
								"west": { "texture": "#brass", "uv": [ 12.0, 5.5, 14.0, 6.0 ], "reflectiveMode": 2},
								"up": { "texture": "#brass", "uv": [ 12.0, 4.5, 13.0, 6.5 ], "reflectiveMode": 2},
								"down": { "texture": "#brass", "uv": [ 7.5, 6.5, 8.5, 8.5 ], "reflectiveMode": 2}
							}
						},
						{
							"name": "innertooth33",
							"from": [ 0.0, 0.0, 0.0 ], 
							"to": [ 1.1, 0.6, 2.02 ], 
							"rotationOrigin": [ -1.7, 0.3, 1.51 ],
							"rotationZ": -112.5,
							"faces": {
								"north": { "texture": "#brass", "uv": [ 9.0, 6.5, 10.0, 7.0 ], "reflectiveMode": 2},
								"east": { "texture": "#brass", "uv": [ 5.5, 10.5, 7.5, 11.0 ], "reflectiveMode": 2},
								"south": { "texture": "#brass", "uv": [ 7.5, 7.0, 8.5, 7.5 ], "reflectiveMode": 2},
								"west": { "texture": "#brass", "uv": [ 9.5, 10.0, 11.5, 10.5 ], "reflectiveMode": 2},
								"up": { "texture": "#brass", "uv": [ 5.0, 7.0, 6.0, 9.0 ], "reflectiveMode": 2},
								"down": { "texture": "#brass", "uv": [ 6.5, 9.5, 7.5, 11.5 ], "reflectiveMode": 2}
							}
						},
						{
							"name": "innertooth34",
							"from": [ 0.0, 0.0, 0.0 ], 
							"to": [ 1.1, 0.6, 2.02 ], 
							"rotationOrigin": [ -1.7, 0.3, 1.51 ],
							"rotationZ": -135.0,
							"faces": {
								"north": { "texture": "#brass", "uv": [ 9.5, 6.5, 10.5, 7.0 ], "reflectiveMode": 2},
								"east": { "texture": "#brass", "uv": [ 8.0, 6.5, 10.0, 7.0 ], "reflectiveMode": 2},
								"south": { "texture": "#brass", "uv": [ 6.5, 7.0, 7.5, 7.5 ], "reflectiveMode": 2},
								"west": { "texture": "#brass", "uv": [ 7.5, 10.5, 9.5, 11.0 ], "reflectiveMode": 2},
								"up": { "texture": "#brass", "uv": [ 6.5, 5.0, 7.5, 7.0 ], "reflectiveMode": 2},
								"down": { "texture": "#brass", "uv": [ 12.5, 3.5, 13.5, 5.5 ], "reflectiveMode": 2}
							}
						},
						{
							"name": "innertooth35",
							"from": [ 0.0, 0.0, 0.0 ], 
							"to": [ 1.1, 0.6, 2.02 ], 
							"rotationOrigin": [ -1.7, 0.3, 1.51 ],
							"rotationZ": -157.5,
							"faces": {
								"north": { "texture": "#brass", "uv": [ 8.5, 5.0, 9.5, 5.5 ], "reflectiveMode": 2},
								"east": { "texture": "#brass", "uv": [ 10.0, 6.0, 12.0, 6.5 ], "reflectiveMode": 2},
								"south": { "texture": "#brass", "uv": [ 10.0, 6.0, 11.0, 6.5 ], "reflectiveMode": 2},
								"west": { "texture": "#brass", "uv": [ 5.0, 7.0, 7.0, 7.5 ], "reflectiveMode": 2},
								"up": { "texture": "#brass", "uv": [ 8.0, 5.5, 9.0, 7.5 ], "reflectiveMode": 2},
								"down": { "texture": "#brass", "uv": [ 5.0, 9.5, 6.0, 11.5 ], "reflectiveMode": 2}
							}
						}
					]
				}
			]
		}
	]}